OneDrive/Desktop/75/week_6/src/fifo/fifo.v
module fifo(
    //depth here is 4 (the slotsss)
    //width here is 2 bit ,ean sthe size of data
    input wire [1:0]data_in,
    output wire [1:0]data_out,
    input wire clk,
    input wire rst,
    input wire wi_en,
    input wire rd_en
);
reg [1:0]mem[0:3];
wire empty;
wire full;
reg [1:0]rd_ptr;
reg [1:0]wr_ptr;
reg[2:0]count;
wire do_write =wi_en&&(!empty||rd_en);
wire do_read=rd_en&&(!full||wi_en);
assign empty=(count==3'd0);
assign full=(count==3'd4);
always @(posedge clk)begin
    if(rst)begin
        rd_ptr=2'd0;
        wr_ptr=2'd0;
        count=3'd0;
    end
    else begin
        if (do_write) begin
        wr_ptr<=wr_ptr+1;
        mem[wr_ptr]<=data_in;
        end
        if (do_read) begin
        rd_ptr<=rd_ptr+1;
        end
        case({do_write, do_read})
        2'd1:count<=count+3'd1;
        2'd2:count<=count-3'd1;
        default:count<=count;
        endcase
    end
end
assign data_out = (empty && wi_en) ? data_in : mem[rd_ptr];
endmodule

OneDrive/Desktop/75/week_6/src/fifo/tb_fifo2.v
module tb_fifo1;
    reg clk;
    reg rst;
    reg [1:0]data_in;
    reg wi_en;
    reg rd_en;
    wire [1:0]data_out;
    fifo uut(
        .rst(rst), .clk(clk), .data_out(data_out), .data_in(data_in), .wi_en(wi_en), .rd_en(rd_en)
    );
    always #5 clk=~clk;
    initial begin 
        $dumpfile("dump.vcd");
        $dumpvars(0,tb_fifo1);
        clk     = 0;
        rst     = 1;
        wi_en   = 0;
        rd_en   = 0;
        #10;
        rst=0;#5;
        rst=0;wi_en=1;rd_en=0;data_in=2'd0;#10;
        wi_en=1;rd_en=0;data_in=2'd1;#10;
        wi_en=1;rd_en=0;data_in=2'd2;#10;
        wi_en=1;rd_en=0;data_in=2'd3;#10;
        wi_en=1;rd_en=0;data_in=2'd1;#10;
        wi_en=0;rd_en=1;#100;

        $finish;
    end
endmodule

OneDrive/Desktop/75/week_6/src/fifo/dump.vcd
$date
	Mon Jun 22 01:38:07 2026
$end
$version
	Icarus Verilog
$end
$timescale
	1s
$end
$scope module tb_fifo1 $end
$var wire 2 ! data_out [1:0] $end
$var reg 1 " clk $end
$var reg 2 # data_in [1:0] $end
$var reg 1 $ rd_en $end
$var reg 1 % rst $end
$var reg 1 & wi_en $end
$scope module uut $end
$var wire 1 " clk $end
$var wire 2 ' data_in [1:0] $end
$var wire 1 ( do_read $end
$var wire 1 ) do_write $end
$var wire 1 $ rd_en $end
$var wire 1 % rst $end
$var wire 1 & wi_en $end
$var wire 1 * full $end
$var wire 1 + empty $end
$var wire 2 , data_out [1:0] $end
$var reg 3 - count [2:0] $end
$var reg 2 . rd_ptr [1:0] $end
$var reg 2 / wr_ptr [1:0] $end
$upscope $end
$upscope $end
$enddefinitions $end
#0
$dumpvars
bx /
bx .
bx -
bx ,
x+
x*
0)
0(
bx '
0&
1%
0$
bx #
0"
bx !
$end
#5
1+
0*
b0 -
b0 /
b0 .
1"
#10
0"
0%
#15
b0 !
b0 ,
1"
b0 #
b0 '
1&
#20
0"
#25
b1 !
b1 ,
1"
b1 #
b1 '
#30
0"
#35
0+
b1 -
b1 .
1)
bx !
bx ,
1(
1"
b10 #
b10 '
1$
#40
0"
#45
0)
b11 !
b11 ,
1+
b0 -
b1 /
0(
1"
b11 #
b11 '
0$
#50
0"
#55
0+
b1 -
b10 .
1)
bx !
bx ,
1(
1"
b1 #
b1 '
1$
#60
0"
#65
b11 .
b10 /
1"
