OneDrive/Desktop/75/week_5/src/traffic_light/traffic.v
module traffic (
    output reg o_red,
    output reg o_yellow,
    output reg o_green,
    input wire rst,
    input wire clk
);
reg [1:0]st;
localparam red=2'b00;
localparam yellow=2'b01;
localparam green=2'b10;
reg [4:0]timer_limit;
reg [4:0]baud_count;
always @(posedge clk) begin
    if (rst) begin
        baud_count <= 5'd0;
    end
    else begin
        if (baud_count == timer_limit - 5'd1) begin
            baud_count <= 5'd0; 
        end
        else begin
            baud_count <= baud_count + 5'd1;
        end
    end
end
always @(posedge clk) begin
    if(rst) begin
        timer_limit<=1'b0;
        o_green<=1'b0;
        o_red<=1'b0;
        o_yellow<=1'b0;
        st<=red;
    end
    else begin
        case(st)
            red:begin
                timer_limit<=5'd30;
                o_red<=1'b1;
                o_green<=1'b0;
                o_yellow<=1'b0;
                if(baud_count==timer_limit-1) begin
                    st<=yellow;
                end
            end
            yellow:begin
                timer_limit<=5'd5;
                o_red<=1'b0;
                o_green<=1'b0;
                o_yellow<=1'b1;
                if(baud_count==timer_limit-1) begin
                    st<=green;
                
                end
            end
            green:begin
                timer_limit<=5'd25;
                o_red<=1'b0;
                o_green<=1'b1;
                o_yellow<=1'b0;
                if(baud_count==timer_limit-1) begin
                    st<=red;
                
                end
            end
            default:st<=red;
        endcase
    end
end
endmodule

OneDrive/Desktop/75/week_7/src/wed/tb_traffic.v
module tb_traffic;
    wire o_red;
    wire o_yellow;
    wire o_green;
    reg rst;
    reg clk;
    traffic uut(
        .clk(clk), .rst(rst), .o_yellow(o_yellow), .o_red(o_red), .o_green(o_green)
    );
    always #5 clk=~clk; 
    initial begin
        $dumpfile("dump.vcd");
        $dumpvars(0,tb_traffic);
        rst=0;clk=0;#3;
        rst=1;#3;
        rst=0;#1500;
        $finish;
    end
endmodule

OneDrive/Desktop/75/week_5/src/traffic_light/dump.vcd
$date
	Sat Jun 13 23:07:34 2026
$end
$version
	Icarus Verilog
$end
$timescale
	1s
$end
$scope module tb_traffic $end
$var wire 1 ! o_yellow $end
$var wire 1 " o_red $end
$var wire 1 # o_green $end
$var reg 1 $ clk $end
$var reg 1 % rst $end
$scope module uut $end
$var wire 1 $ clk $end
$var wire 1 % rst $end
$var reg 5 & baud_count [4:0] $end
$var reg 1 # o_green $end
$var reg 1 " o_red $end
$var reg 1 ! o_yellow $end
$var reg 2 ' st [1:0] $end
$var reg 5 ( timer_limit [4:0] $end
$upscope $end
$upscope $end
$enddefinitions $end
#0
$dumpvars
bx (
bx '
bx &
0%
0$
x#
x"
x!
$end
#3
1%
#5
b0 &
b0 '
0!
0"
0#
b0 (
1$
#6
0%
#10
0$
#15
1"
b11110 (
b1 &
1$
#20
0$
#25
b10 &
1$
#30
0$
#35
b11 &
1$
#40
0$
#45
b100 &
1$
#50
0$
#55
b101 &
1$
#60
0$
#65
b110 &
1$
#70
0$
#75
b111 &
1$
#80
0$
#85
b1000 &
1$
#90
0$
#95
b1001 &
1$
#100
0$
#105
b1010 &
1$
#110
0$
#115
b1011 &
1$
#120
0$
#125
b1100 &
1$
#130
0$
#135
b1101 &
1$
#140
0$
#145
b1110 &
1$
#150
0$
#155
b1111 &
1$
#160
0$
#165
b10000 &
1$
#170
0$
#175
b10001 &
1$
#180
0$
#185
b10010 &
1$
#190
0$
#195
b10011 &
1$
#200
0$
#205
b10100 &
1$
#210
0$
#215
b10101 &
1$
#220
0$
#225
b10110 &
1$
#230
0$
#235
b10111 &
1$
#240
0$
#245
b11000 &
1$
#250
0$
#255
b11001 &
1$
#260
0$
#265
b11010 &
1$
#270
0$
#275
b11011 &
1$
#280
0$
#285
b11100 &
1$
#290
0$
#295
b11101 &
1$
#300
0$
#305
b0 &
b1 '
1$
#310
0$
#315
1!
0"
b101 (
b1 &
1$
#320
0$
#325
b10 &
1$
#330
0$
#335
b11 &
1$
#340
0$
#345
b100 &
1$
#350
0$
#355
b10 '
b0 &
1$
#360
0$
#365
b1 &
0!
1#
b11001 (
1$
#370
0$
#375
b10 &
1$
#380
0$
#385
b11 &
1$
#390
0$
#395
b100 &
1$
#400
0$
#405
b101 &
1$
#410
0$
#415
b110 &
1$
#420
0$
#425
b111 &
1$
#430
0$
#435
b1000 &
1$
#440
0$
#445
b1001 &
1$
#450
0$
#455
b1010 &
1$
#460
0$
#465
b1011 &
1$
#470
0$
#475
b1100 &
1$
#480
0$
#485
b1101 &
1$
#490
0$
#495
b1110 &
1$
#500
0$
#505
b1111 &
1$
#510
0$
#515
b10000 &
1$
#520
0$
#525
b10001 &
1$
#530
0$
#535
b10010 &
1$
#540
0$
#545
b10011 &
1$
#550
0$
#555
b10100 &
1$
#560
0$
#565
b10101 &
1$
#570
0$
#575
b10110 &
1$
#580
0$
#585
b10111 &
1$
#590
0$
#595
b11000 &
1$
#600
0$
#605
b0 &
b0 '
1$
#610
0$
#615
0#
1"
b11110 (
b1 &
1$
#620
0$
#625
b10 &
1$
#630
0$
#635
b11 &
1$
#640
0$
#645
b100 &
1$
#650
0$
#655
b101 &
1$
#660
0$
#665
b110 &
1$
#670
0$
#675
b111 &
1$
#680
0$
#685
b1000 &
1$
#690
0$
#695
b1001 &
1$
#700
0$
#705
b1010 &
1$
#710
0$
#715
b1011 &
1$
#720
0$
#725
b1100 &
1$
#730
0$
#735
b1101 &
1$
#740
0$
#745
b1110 &
1$
#750
0$
#755
b1111 &
1$
#760
0$
#765
b10000 &
1$
#770
0$
#775
b10001 &
1$
#780
0$
#785
b10010 &
1$
#790
0$
#795
b10011 &
1$
#800
0$
#805
b10100 &
1$
#810
0$
#815
b10101 &
1$
#820
0$
#825
b10110 &
1$
#830
0$
#835
b10111 &
1$
#840
0$
#845
b11000 &
1$
#850
0$
#855
b11001 &
1$
#860
0$
#865
b11010 &
1$
#870
0$
#875
b11011 &
1$
#880
0$
#885
b11100 &
1$
#890
0$
#895
b11101 &
1$
#900
0$
#905
b0 &
b1 '
1$
#910
0$
#915
1!
0"
b101 (
b1 &
1$
#920
0$
#925
b10 &
1$
#930
0$
#935
b11 &
1$
#940
0$
#945
b100 &
1$
#950
0$
#955
b10 '
b0 &
1$
#960
0$
#965
b1 &
0!
1#
b11001 (
1$
#970
0$
#975
b10 &
1$
#980
0$
#985
b11 &
1$
#990
0$
#995
b100 &
1$
#1000
0$
#1005
b101 &
1$
#1010
0$
#1015
b110 &
1$
#1020
0$
#1025
b111 &
1$
#1030
0$
#1035
b1000 &
1$
#1040
0$
#1045
b1001 &
1$
#1050
0$
#1055
b1010 &
1$
#1060
0$
#1065
b1011 &
1$
#1070
0$
#1075
b1100 &
1$
#1080
0$
#1085
b1101 &
1$
#1090
0$
#1095
b1110 &
1$
#1100
0$
#1105
b1111 &
1$
#1110
0$
#1115
b10000 &
1$
#1120
0$
#1125
b10001 &
1$
#1130
0$
#1135
b10010 &
1$
#1140
0$
#1145
b10011 &
1$
#1150
0$
#1155
b10100 &
1$
#1160
0$
#1165
b10101 &
1$
#1170
0$
#1175
b10110 &
1$
#1180
0$
#1185
b10111 &
1$
#1190
0$
#1195
b11000 &
1$
#1200
0$
#1205
b0 &
b0 '
1$
#1210
0$
#1215
0#
1"
b11110 (
b1 &
1$
#1220
0$
#1225
b10 &
1$
#1230
0$
#1235
b11 &
1$
#1240
0$
#1245
b100 &
1$
#1250
0$
#1255
b101 &
1$
#1260
0$
#1265
b110 &
1$
#1270
0$
#1275
b111 &
1$
#1280
0$
#1285
b1000 &
1$
#1290
0$
#1295
b1001 &
1$
#1300
0$
#1305
b1010 &
1$
#1310
0$
#1315
b1011 &
1$
#1320
0$
#1325
b1100 &
1$
#1330
0$
#1335
b1101 &
1$
#1340
0$
#1345
b1110 &
1$
#1350
0$
#1355
b1111 &
1$
#1360
0$
#1365
b10000 &
1$
#1370
0$
#1375
b10001 &
1$
#1380
0$
#1385
b10010 &
1$
#1390
0$
#1395
b10011 &
1$
#1400
0$
#1405
b10100 &
1$
#1410
0$
#1415
b10101 &
1$
#1420
0$
#1425
b10110 &
1$
#1430
0$
#1435
b10111 &
1$
#1440
0$
#1445
b11000 &
1$
#1450
0$
#1455
b11001 &
1$
#1460
0$
#1465
b11010 &
1$
#1470
0$
#1475
b11011 &
1$
#1480
0$
#1485
b11100 &
1$
#1490
0$
#1495
b11101 &
1$
#1500
0$
#1505
b0 &
b1 '
1$
