OneDrive/Desktop/75/week_7/src/adder/adder.v
module adder(
    input wire [3:0]a,
    input wire [3:0]b,
    output wire [4:0]sum
);
    assign sum= a+b;
endmodule

OneDrive/Desktop/75/week_7/src/wed/tb_adder.v
module tb_adder;
    reg [3:0]a;
    reg [3:0]b;
    wire [4:0]sum;
    adder uut(
        .sum(sum), .a(a), .b(b)
    );
    integer i ,j;
    integer expected;
    initial begin
        $dumpfile("dump.vcd");
        $dumpvars(0,tb_adder);
        for(j=0;j<16;j=j+1)begin
            for(i=0;i<16;i=i+1)begin
                a=i;
                b=j; 
                expected = a + b; 
                #1;
                if (sum === expected) begin
                    $display("PASS: a=%d b=%d expected=%d got=%d", a, b, expected, sum);
                end else begin
                    $display("FAIL: a=%d b=%d expected=%d got=%d", a, b, expected, sum);
                end
                #5;
            end
        end
    end
endmodule

OneDrive/Desktop/75/week_7/src/adder/dump.vcd
$date
	Mon Jun 22 23:50:38 2026
$end
$version
	Icarus Verilog
$end
$timescale
	1s
$end
$scope module tb_adder $end
$var wire 5 ! sum [4:0] $end
$var reg 4 " a [3:0] $end
$var reg 4 # b [3:0] $end
$var integer 32 $ expected [31:0] $end
$var integer 32 % i [31:0] $end
$var integer 32 & j [31:0] $end
$scope module uut $end
$var wire 4 ' a [3:0] $end
$var wire 4 ( b [3:0] $end
$var wire 5 ) sum [4:0] $end
$upscope $end
$upscope $end
$enddefinitions $end
#0
$dumpvars
b0 )
b0 (
b0 '
b0 &
b0 %
b0 $
b0 #
b0 "
b0 !
$end
#6
b1 $
b1 !
b1 )
b1 "
b1 '
b1 %
#12
b10 $
b10 !
b10 )
b10 "
b10 '
b10 %
#18
b11 $
b11 !
b11 )
b11 "
b11 '
b11 %
#24
b100 $
b100 !
b100 )
b100 "
b100 '
b100 %
#30
b101 $
b101 !
b101 )
b101 "
b101 '
b101 %
#36
b110 $
b110 !
b110 )
b110 "
b110 '
b110 %
#42
b111 $
b111 !
b111 )
b111 "
b111 '
b111 %
#48
b1000 $
b1000 !
b1000 )
b1000 "
b1000 '
b1000 %
#54
b1001 $
b1001 !
b1001 )
b1001 "
b1001 '
b1001 %
#60
b1010 $
b1010 !
b1010 )
b1010 "
b1010 '
b1010 %
#66
b1011 $
b1011 !
b1011 )
b1011 "
b1011 '
b1011 %
#72
b1100 $
b1100 !
b1100 )
b1100 "
b1100 '
b1100 %
#78
b1101 $
b1101 !
b1101 )
b1101 "
b1101 '
b1101 %
#84
b1110 $
b1110 !
b1110 )
b1110 "
b1110 '
b1110 %
#90
b1111 $
b1111 !
b1111 )
b1111 "
b1111 '
b1111 %
#96
b1 $
b1 #
b1 (
b1 !
b1 )
b0 "
b0 '
b1 &
b0 %
#102
b10 $
b10 !
b10 )
b1 "
b1 '
b1 %
#108
b11 $
b11 !
b11 )
b10 "
b10 '
b10 %
#114
b100 $
b100 !
b100 )
b11 "
b11 '
b11 %
#120
b101 $
b101 !
b101 )
b100 "
b100 '
b100 %
#126
b110 $
b110 !
b110 )
b101 "
b101 '
b101 %
#132
b111 $
b111 !
b111 )
b110 "
b110 '
b110 %
#138
b1000 $
b1000 !
b1000 )
b111 "
b111 '
b111 %
#144
b1001 $
b1001 !
b1001 )
b1000 "
b1000 '
b1000 %
#150
b1010 $
b1010 !
b1010 )
b1001 "
b1001 '
b1001 %
#156
b1011 $
b1011 !
b1011 )
b1010 "
b1010 '
b1010 %
#162
b1100 $
b1100 !
b1100 )
b1011 "
b1011 '
b1011 %
#168
b1101 $
b1101 !
b1101 )
b1100 "
b1100 '
b1100 %
#174
b1110 $
b1110 !
b1110 )
b1101 "
b1101 '
b1101 %
#180
b1111 $
b1111 !
b1111 )
b1110 "
b1110 '
b1110 %
#186
b10000 $
b10000 !
b10000 )
b1111 "
b1111 '
b1111 %
#192
b10 $
b10 #
b10 (
b10 !
b10 )
b0 "
b0 '
b10 &
b0 %
#198
b11 $
b11 !
b11 )
b1 "
b1 '
b1 %
#204
b100 $
b100 !
b100 )
b10 "
b10 '
b10 %
#210
b101 $
b101 !
b101 )
b11 "
b11 '
b11 %
#216
b110 $
b110 !
b110 )
b100 "
b100 '
b100 %
#222
b111 $
b111 !
b111 )
b101 "
b101 '
b101 %
#228
b1000 $
b1000 !
b1000 )
b110 "
b110 '
b110 %
#234
b1001 $
b1001 !
b1001 )
b111 "
b111 '
b111 %
#240
b1010 $
b1010 !
b1010 )
b1000 "
b1000 '
b1000 %
#246
b1011 $
b1011 !
b1011 )
b1001 "
b1001 '
b1001 %
#252
b1100 $
b1100 !
b1100 )
b1010 "
b1010 '
b1010 %
#258
b1101 $
b1101 !
b1101 )
b1011 "
b1011 '
b1011 %
#264
b1110 $
b1110 !
b1110 )
b1100 "
b1100 '
b1100 %
#270
b1111 $
b1111 !
b1111 )
b1101 "
b1101 '
b1101 %
#276
b10000 $
b10000 !
b10000 )
b1110 "
b1110 '
b1110 %
#282
b10001 $
b10001 !
b10001 )
b1111 "
b1111 '
b1111 %
#288
b11 $
b11 #
b11 (
b11 !
b11 )
b0 "
b0 '
b11 &
b0 %
#294
b100 $
b100 !
b100 )
b1 "
b1 '
b1 %
#300
b101 $
b101 !
b101 )
b10 "
b10 '
b10 %
#306
b110 $
b110 !
b110 )
b11 "
b11 '
b11 %
#312
b111 $
b111 !
b111 )
b100 "
b100 '
b100 %
#318
b1000 $
b1000 !
b1000 )
b101 "
b101 '
b101 %
#324
b1001 $
b1001 !
b1001 )
b110 "
b110 '
b110 %
#330
b1010 $
b1010 !
b1010 )
b111 "
b111 '
b111 %
#336
b1011 $
b1011 !
b1011 )
b1000 "
b1000 '
b1000 %
#342
b1100 $
b1100 !
b1100 )
b1001 "
b1001 '
b1001 %
#348
b1101 $
b1101 !
b1101 )
b1010 "
b1010 '
b1010 %
#354
b1110 $
b1110 !
b1110 )
b1011 "
b1011 '
b1011 %
#360
b1111 $
b1111 !
b1111 )
b1100 "
b1100 '
b1100 %
#366
b10000 $
b10000 !
b10000 )
b1101 "
b1101 '
b1101 %
#372
b10001 $
b10001 !
b10001 )
b1110 "
b1110 '
b1110 %
#378
b10010 $
b10010 !
b10010 )
b1111 "
b1111 '
b1111 %
#384
b100 $
b100 #
b100 (
b100 !
b100 )
b0 "
b0 '
b100 &
b0 %
#390
b101 $
b101 !
b101 )
b1 "
b1 '
b1 %
#396
b110 $
b110 !
b110 )
b10 "
b10 '
b10 %
#402
b111 $
b111 !
b111 )
b11 "
b11 '
b11 %
#408
b1000 $
b1000 !
b1000 )
b100 "
b100 '
b100 %
#414
b1001 $
b1001 !
b1001 )
b101 "
b101 '
b101 %
#420
b1010 $
b1010 !
b1010 )
b110 "
b110 '
b110 %
#426
b1011 $
b1011 !
b1011 )
b111 "
b111 '
b111 %
#432
b1100 $
b1100 !
b1100 )
b1000 "
b1000 '
b1000 %
#438
b1101 $
b1101 !
b1101 )
b1001 "
b1001 '
b1001 %
#444
b1110 $
b1110 !
b1110 )
b1010 "
b1010 '
b1010 %
#450
b1111 $
b1111 !
b1111 )
b1011 "
b1011 '
b1011 %
#456
b10000 $
b10000 !
b10000 )
b1100 "
b1100 '
b1100 %
#462
b10001 $
b10001 !
b10001 )
b1101 "
b1101 '
b1101 %
#468
b10010 $
b10010 !
b10010 )
b1110 "
b1110 '
b1110 %
#474
b10011 $
b10011 !
b10011 )
b1111 "
b1111 '
b1111 %
#480
b101 $
b101 #
b101 (
b101 !
b101 )
b0 "
b0 '
b101 &
b0 %
#486
b110 $
b110 !
b110 )
b1 "
b1 '
b1 %
#492
b111 $
b111 !
b111 )
b10 "
b10 '
b10 %
#498
b1000 $
b1000 !
b1000 )
b11 "
b11 '
b11 %
#504
b1001 $
b1001 !
b1001 )
b100 "
b100 '
b100 %
#510
b1010 $
b1010 !
b1010 )
b101 "
b101 '
b101 %
#516
b1011 $
b1011 !
b1011 )
b110 "
b110 '
b110 %
#522
b1100 $
b1100 !
b1100 )
b111 "
b111 '
b111 %
#528
b1101 $
b1101 !
b1101 )
b1000 "
b1000 '
b1000 %
#534
b1110 $
b1110 !
b1110 )
b1001 "
b1001 '
b1001 %
#540
b1111 $
b1111 !
b1111 )
b1010 "
b1010 '
b1010 %
#546
b10000 $
b10000 !
b10000 )
b1011 "
b1011 '
b1011 %
#552
b10001 $
b10001 !
b10001 )
b1100 "
b1100 '
b1100 %
#558
b10010 $
b10010 !
b10010 )
b1101 "
b1101 '
b1101 %
#564
b10011 $
b10011 !
b10011 )
b1110 "
b1110 '
b1110 %
#570
b10100 $
b10100 !
b10100 )
b1111 "
b1111 '
b1111 %
#576
b110 $
b110 #
b110 (
b110 !
b110 )
b0 "
b0 '
b110 &
b0 %
#582
b111 $
b111 !
b111 )
b1 "
b1 '
b1 %
#588
b1000 $
b1000 !
b1000 )
b10 "
b10 '
b10 %
#594
b1001 $
b1001 !
b1001 )
b11 "
b11 '
b11 %
#600
b1010 $
b1010 !
b1010 )
b100 "
b100 '
b100 %
#606
b1011 $
b1011 !
b1011 )
b101 "
b101 '
b101 %
#612
b1100 $
b1100 !
b1100 )
b110 "
b110 '
b110 %
#618
b1101 $
b1101 !
b1101 )
b111 "
b111 '
b111 %
#624
b1110 $
b1110 !
b1110 )
b1000 "
b1000 '
b1000 %
#630
b1111 $
b1111 !
b1111 )
b1001 "
b1001 '
b1001 %
#636
b10000 $
b10000 !
b10000 )
b1010 "
b1010 '
b1010 %
#642
b10001 $
b10001 !
b10001 )
b1011 "
b1011 '
b1011 %
#648
b10010 $
b10010 !
b10010 )
b1100 "
b1100 '
b1100 %
#654
b10011 $
b10011 !
b10011 )
b1101 "
b1101 '
b1101 %
#660
b10100 $
b10100 !
b10100 )
b1110 "
b1110 '
b1110 %
#666
b10101 $
b10101 !
b10101 )
b1111 "
b1111 '
b1111 %
#672
b111 $
b111 #
b111 (
b111 !
b111 )
b0 "
b0 '
b111 &
b0 %
#678
b1000 $
b1000 !
b1000 )
b1 "
b1 '
b1 %
#684
b1001 $
b1001 !
b1001 )
b10 "
b10 '
b10 %
#690
b1010 $
b1010 !
b1010 )
b11 "
b11 '
b11 %
#696
b1011 $
b1011 !
b1011 )
b100 "
b100 '
b100 %
#702
b1100 $
b1100 !
b1100 )
b101 "
b101 '
b101 %
#708
b1101 $
b1101 !
b1101 )
b110 "
b110 '
b110 %
#714
b1110 $
b1110 !
b1110 )
b111 "
b111 '
b111 %
#720
b1111 $
b1111 !
b1111 )
b1000 "
b1000 '
b1000 %
#726
b10000 $
b10000 !
b10000 )
b1001 "
b1001 '
b1001 %
#732
b10001 $
b10001 !
b10001 )
b1010 "
b1010 '
b1010 %
#738
b10010 $
b10010 !
b10010 )
b1011 "
b1011 '
b1011 %
#744
b10011 $
b10011 !
b10011 )
b1100 "
b1100 '
b1100 %
#750
b10100 $
b10100 !
b10100 )
b1101 "
b1101 '
b1101 %
#756
b10101 $
b10101 !
b10101 )
b1110 "
b1110 '
b1110 %
#762
b10110 $
b10110 !
b10110 )
b1111 "
b1111 '
b1111 %
#768
b1000 $
b1000 #
b1000 (
b1000 !
b1000 )
b0 "
b0 '
b1000 &
b0 %
#774
b1001 $
b1001 !
b1001 )
b1 "
b1 '
b1 %
#780
b1010 $
b1010 !
b1010 )
b10 "
b10 '
b10 %
#786
b1011 $
b1011 !
b1011 )
b11 "
b11 '
b11 %
#792
b1100 $
b1100 !
b1100 )
b100 "
b100 '
b100 %
#798
b1101 $
b1101 !
b1101 )
b101 "
b101 '
b101 %
#804
b1110 $
b1110 !
b1110 )
b110 "
b110 '
b110 %
#810
b1111 $
b1111 !
b1111 )
b111 "
b111 '
b111 %
#816
b10000 $
b10000 !
b10000 )
b1000 "
b1000 '
b1000 %
#822
b10001 $
b10001 !
b10001 )
b1001 "
b1001 '
b1001 %
#828
b10010 $
b10010 !
b10010 )
b1010 "
b1010 '
b1010 %
#834
b10011 $
b10011 !
b10011 )
b1011 "
b1011 '
b1011 %
#840
b10100 $
b10100 !
b10100 )
b1100 "
b1100 '
b1100 %
#846
b10101 $
b10101 !
b10101 )
b1101 "
b1101 '
b1101 %
#852
b10110 $
b10110 !
b10110 )
b1110 "
b1110 '
b1110 %
#858
b10111 $
b10111 !
b10111 )
b1111 "
b1111 '
b1111 %
#864
b1001 $
b1001 #
b1001 (
b1001 !
b1001 )
b0 "
b0 '
b1001 &
b0 %
#870
b1010 $
b1010 !
b1010 )
b1 "
b1 '
b1 %
#876
b1011 $
b1011 !
b1011 )
b10 "
b10 '
b10 %
#882
b1100 $
b1100 !
b1100 )
b11 "
b11 '
b11 %
#888
b1101 $
b1101 !
b1101 )
b100 "
b100 '
b100 %
#894
b1110 $
b1110 !
b1110 )
b101 "
b101 '
b101 %
#900
b1111 $
b1111 !
b1111 )
b110 "
b110 '
b110 %
#906
b10000 $
b10000 !
b10000 )
b111 "
b111 '
b111 %
#912
b10001 $
b10001 !
b10001 )
b1000 "
b1000 '
b1000 %
#918
b10010 $
b10010 !
b10010 )
b1001 "
b1001 '
b1001 %
#924
b10011 $
b10011 !
b10011 )
b1010 "
b1010 '
b1010 %
#930
b10100 $
b10100 !
b10100 )
b1011 "
b1011 '
b1011 %
#936
b10101 $
b10101 !
b10101 )
b1100 "
b1100 '
b1100 %
#942
b10110 $
b10110 !
b10110 )
b1101 "
b1101 '
b1101 %
#948
b10111 $
b10111 !
b10111 )
b1110 "
b1110 '
b1110 %
#954
b11000 $
b11000 !
b11000 )
b1111 "
b1111 '
b1111 %
#960
b1010 $
b1010 #
b1010 (
b1010 !
b1010 )
b0 "
b0 '
b1010 &
b0 %
#966
b1011 $
b1011 !
b1011 )
b1 "
b1 '
b1 %
#972
b1100 $
b1100 !
b1100 )
b10 "
b10 '
b10 %
#978
b1101 $
b1101 !
b1101 )
b11 "
b11 '
b11 %
#984
b1110 $
b1110 !
b1110 )
b100 "
b100 '
b100 %
#990
b1111 $
b1111 !
b1111 )
b101 "
b101 '
b101 %
#996
b10000 $
b10000 !
b10000 )
b110 "
b110 '
b110 %
#1002
b10001 $
b10001 !
b10001 )
b111 "
b111 '
b111 %
#1008
b10010 $
b10010 !
b10010 )
b1000 "
b1000 '
b1000 %
#1014
b10011 $
b10011 !
b10011 )
b1001 "
b1001 '
b1001 %
#1020
b10100 $
b10100 !
b10100 )
b1010 "
b1010 '
b1010 %
#1026
b10101 $
b10101 !
b10101 )
b1011 "
b1011 '
b1011 %
#1032
b10110 $
b10110 !
b10110 )
b1100 "
b1100 '
b1100 %
#1038
b10111 $
b10111 !
b10111 )
b1101 "
b1101 '
b1101 %
#1044
b11000 $
b11000 !
b11000 )
b1110 "
b1110 '
b1110 %
#1050
b11001 $
b11001 !
b11001 )
b1111 "
b1111 '
b1111 %
#1056
b1011 $
b1011 #
b1011 (
b1011 !
b1011 )
b0 "
b0 '
b1011 &
b0 %
#1062
b1100 $
b1100 !
b1100 )
b1 "
b1 '
b1 %
#1068
b1101 $
b1101 !
b1101 )
b10 "
b10 '
b10 %
#1074
b1110 $
b1110 !
b1110 )
b11 "
b11 '
b11 %
#1080
b1111 $
b1111 !
b1111 )
b100 "
b100 '
b100 %
#1086
b10000 $
b10000 !
b10000 )
b101 "
b101 '
b101 %
#1092
b10001 $
b10001 !
b10001 )
b110 "
b110 '
b110 %
#1098
b10010 $
b10010 !
b10010 )
b111 "
b111 '
b111 %
#1104
b10011 $
b10011 !
b10011 )
b1000 "
b1000 '
b1000 %
#1110
b10100 $
b10100 !
b10100 )
b1001 "
b1001 '
b1001 %
#1116
b10101 $
b10101 !
b10101 )
b1010 "
b1010 '
b1010 %
#1122
b10110 $
b10110 !
b10110 )
b1011 "
b1011 '
b1011 %
#1128
b10111 $
b10111 !
b10111 )
b1100 "
b1100 '
b1100 %
#1134
b11000 $
b11000 !
b11000 )
b1101 "
b1101 '
b1101 %
#1140
b11001 $
b11001 !
b11001 )
b1110 "
b1110 '
b1110 %
#1146
b11010 $
b11010 !
b11010 )
b1111 "
b1111 '
b1111 %
#1152
b1100 $
b1100 #
b1100 (
b1100 !
b1100 )
b0 "
b0 '
b1100 &
b0 %
#1158
b1101 $
b1101 !
b1101 )
b1 "
b1 '
b1 %
#1164
b1110 $
b1110 !
b1110 )
b10 "
b10 '
b10 %
#1170
b1111 $
b1111 !
b1111 )
b11 "
b11 '
b11 %
#1176
b10000 $
b10000 !
b10000 )
b100 "
b100 '
b100 %
#1182
b10001 $
b10001 !
b10001 )
b101 "
b101 '
b101 %
#1188
b10010 $
b10010 !
b10010 )
b110 "
b110 '
b110 %
#1194
b10011 $
b10011 !
b10011 )
b111 "
b111 '
b111 %
#1200
b10100 $
b10100 !
b10100 )
b1000 "
b1000 '
b1000 %
#1206
b10101 $
b10101 !
b10101 )
b1001 "
b1001 '
b1001 %
#1212
b10110 $
b10110 !
b10110 )
b1010 "
b1010 '
b1010 %
#1218
b10111 $
b10111 !
b10111 )
b1011 "
b1011 '
b1011 %
#1224
b11000 $
b11000 !
b11000 )
b1100 "
b1100 '
b1100 %
#1230
b11001 $
b11001 !
b11001 )
b1101 "
b1101 '
b1101 %
#1236
b11010 $
b11010 !
b11010 )
b1110 "
b1110 '
b1110 %
#1242
b11011 $
b11011 !
b11011 )
b1111 "
b1111 '
b1111 %
#1248
b1101 $
b1101 #
b1101 (
b1101 !
b1101 )
b0 "
b0 '
b1101 &
b0 %
#1254
b1110 $
b1110 !
b1110 )
b1 "
b1 '
b1 %
#1260
b1111 $
b1111 !
b1111 )
b10 "
b10 '
b10 %
#1266
b10000 $
b10000 !
b10000 )
b11 "
b11 '
b11 %
#1272
b10001 $
b10001 !
b10001 )
b100 "
b100 '
b100 %
#1278
b10010 $
b10010 !
b10010 )
b101 "
b101 '
b101 %
#1284
b10011 $
b10011 !
b10011 )
b110 "
b110 '
b110 %
#1290
b10100 $
b10100 !
b10100 )
b111 "
b111 '
b111 %
#1296
b10101 $
b10101 !
b10101 )
b1000 "
b1000 '
b1000 %
#1302
b10110 $
b10110 !
b10110 )
b1001 "
b1001 '
b1001 %
#1308
b10111 $
b10111 !
b10111 )
b1010 "
b1010 '
b1010 %
#1314
b11000 $
b11000 !
b11000 )
b1011 "
b1011 '
b1011 %
#1320
b11001 $
b11001 !
b11001 )
b1100 "
b1100 '
b1100 %
#1326
b11010 $
b11010 !
b11010 )
b1101 "
b1101 '
b1101 %
#1332
b11011 $
b11011 !
b11011 )
b1110 "
b1110 '
b1110 %
#1338
b11100 $
b11100 !
b11100 )
b1111 "
b1111 '
b1111 %
#1344
b1110 $
b1110 #
b1110 (
b1110 !
b1110 )
b0 "
b0 '
b1110 &
b0 %
#1350
b1111 $
b1111 !
b1111 )
b1 "
b1 '
b1 %
#1356
b10000 $
b10000 !
b10000 )
b10 "
b10 '
b10 %
#1362
b10001 $
b10001 !
b10001 )
b11 "
b11 '
b11 %
#1368
b10010 $
b10010 !
b10010 )
b100 "
b100 '
b100 %
#1374
b10011 $
b10011 !
b10011 )
b101 "
b101 '
b101 %
#1380
b10100 $
b10100 !
b10100 )
b110 "
b110 '
b110 %
#1386
b10101 $
b10101 !
b10101 )
b111 "
b111 '
b111 %
#1392
b10110 $
b10110 !
b10110 )
b1000 "
b1000 '
b1000 %
#1398
b10111 $
b10111 !
b10111 )
b1001 "
b1001 '
b1001 %
#1404
b11000 $
b11000 !
b11000 )
b1010 "
b1010 '
b1010 %
#1410
b11001 $
b11001 !
b11001 )
b1011 "
b1011 '
b1011 %
#1416
b11010 $
b11010 !
b11010 )
b1100 "
b1100 '
b1100 %
#1422
b11011 $
b11011 !
b11011 )
b1101 "
b1101 '
b1101 %
#1428
b11100 $
b11100 !
b11100 )
b1110 "
b1110 '
b1110 %
#1434
b11101 $
b11101 !
b11101 )
b1111 "
b1111 '
b1111 %
#1440
b1111 $
b1111 #
b1111 (
b1111 !
b1111 )
b0 "
b0 '
b1111 &
b0 %
#1446
b10000 $
b10000 !
b10000 )
b1 "
b1 '
b1 %
#1452
b10001 $
b10001 !
b10001 )
b10 "
b10 '
b10 %
#1458
b10010 $
b10010 !
b10010 )
b11 "
b11 '
b11 %
#1464
b10011 $
b10011 !
b10011 )
b100 "
b100 '
b100 %
#1470
b10100 $
b10100 !
b10100 )
b101 "
b101 '
b101 %
#1476
b10101 $
b10101 !
b10101 )
b110 "
b110 '
b110 %
#1482
b10110 $
b10110 !
b10110 )
b111 "
b111 '
b111 %
#1488
b10111 $
b10111 !
b10111 )
b1000 "
b1000 '
b1000 %
#1494
b11000 $
b11000 !
b11000 )
b1001 "
b1001 '
b1001 %
#1500
b11001 $
b11001 !
b11001 )
b1010 "
b1010 '
b1010 %
#1506
b11010 $
b11010 !
b11010 )
b1011 "
b1011 '
b1011 %
#1512
b11011 $
b11011 !
b11011 )
b1100 "
b1100 '
b1100 %
#1518
b11100 $
b11100 !
b11100 )
b1101 "
b1101 '
b1101 %
#1524
b11101 $
b11101 !
b11101 )
b1110 "
b1110 '
b1110 %
#1530
b11110 $
b11110 !
b11110 )
b1111 "
b1111 '
b1111 %
#1536
b10000 &
b10000 %
