OneDrive/Desktop/75/week_3/src/pipelinebug/pipelinebug.v
module pipelinebug(
    input wire clk,
    input wire rst,
    input wire d,
    output reg q1,
    output reg q2
); 
   always@(posedge clk) begin
    q1=d;
    q2=q1;
   end
endmodule

OneDrive/Desktop/75/week_3/src/pipelinebug/tb_pipelinebug.v
`timescale 1ns/1ps

module tb_pipelinebug;


    reg clk;
    reg rst;
    reg d;
    wire q1;
    wire q2;
    pipelinebug uut(
        .clk(clk),
        .rst(rst), 
        .d(d),
        .q1(q1),
        .q2(q2)
    );
    always #5 clk = ~clk;
    initial begin
        $dumpfile("dump.vcd");
        $dumpvars(0, tb_pipelinebug);
        

        clk = 0; rst = 0; d = 0;
        #2 rst = 1;
        #10 rst = 0;
        #6 d = 1;
        #30; 
        d = 0;  
        #30;
        $finish; 
    end

endmodule

OneDrive/Desktop/75/week_3/src/pipelinebug/dump.vcd
$date
	Thu Jun 04 12:41:48 2026
$end
$version
	Icarus Verilog
$end
$timescale
	1ps
$end
$scope module tb_pipelinebug $end
$var wire 1 ! q2 $end
$var wire 1 " q1 $end
$var reg 1 # clk $end
$var reg 1 $ d $end
$var reg 1 % rst $end
$scope module uut $end
$var wire 1 # clk $end
$var wire 1 $ d $end
$var wire 1 % rst $end
$var reg 1 " q1 $end
$var reg 1 ! q2 $end
$upscope $end
$upscope $end
$enddefinitions $end
#0
$dumpvars
0%
0$
0#
x"
x!
$end
#2000
1%
#5000
0!
0"
1#
#10000
0#
#12000
0%
#15000
1#
#18000
1$
#20000
0#
#25000
1!
1"
1#
#30000
0#
#35000
1#
#40000
0#
#45000
1#
#48000
0$
#50000
0#
#55000
0!
0"
1#
