OneDrive/Desktop/75/week_5/src/vending/vending.v
module vending(
    input wire coin_5p,
    input wire coin_10p,
    input wire coin_25p,
    output reg dispenceo,
    input wire rst,
    input wire clk

);
reg [1:0]st;
localparam idle =2'b00;
localparam add =2'b01;
localparam dispense =2'b10;
reg [5:0]balance;
always @(posedge clk) begin
    if(rst) begin
        balance<=6'd0;
        dispenceo<=0;
        st<=idle;
    end
    else begin
    case(st)
        idle:begin
            if(coin_5p||coin_10p||coin_25p) begin
                st<=add;
            end
        end
        add:begin
            if(coin_5p)begin
                balance<=balance+6'd5;
            end
            else if(coin_10p)begin
                balance<=balance+6'd10;
            end
            else if (coin_25p)begin
                balance<=balance+6'd25;
            end
            if(balance>=6'd30) begin
                st<=dispense;
                balance<=6'd0;
            end
        end
        dispense:begin
            dispenceo<=1'b1;
            balance<=6'd0;
            st<=idle;
        end

        default st<=idle;
    endcase
    end

end
endmodule

OneDrive/Desktop/75/week_5/src/vending/tb_vending.v
module tb_vending;
    reg clk;
    reg rst;
    reg coin_5p;
    reg coin_10p;
    reg coin_25p;
    wire dispenceo;
    vending uut(
        .clk(clk), .rst(rst), .coin_5p(coin_5p), .coin_10p(coin_10p), .coin_25p(coin_25p), .dispenceo(dispenceo)
    );
    always #5 clk=~clk;
    initial begin
        $dumpfile("dump.vcd");
        $dumpvars(0,tb_vending);
        rst=0;clk=0;#3;
        rst=1;#3;
        rst=0;coin_5p=1;coin_10p=1;coin_25p=1;#200;
        $finish;
    end
endmodule

OneDrive/Desktop/75/week_5/src/vending/dump.vcd
$date
	Thu Jun 18 01:32:38 2026
$end
$version
	Icarus Verilog
$end
$timescale
	1s
$end
$scope module tb_vending $end
$var wire 1 ! dispenceo $end
$var reg 1 " clk $end
$var reg 1 # coin_10p $end
$var reg 1 $ coin_25p $end
$var reg 1 % coin_5p $end
$var reg 1 & rst $end
$scope module uut $end
$var wire 1 " clk $end
$var wire 1 # coin_10p $end
$var wire 1 $ coin_25p $end
$var wire 1 % coin_5p $end
$var wire 1 & rst $end
$var reg 6 ' balance [5:0] $end
$var reg 1 ! dispenceo $end
$var reg 2 ( st [1:0] $end
$upscope $end
$upscope $end
$enddefinitions $end
#0
$dumpvars
bx (
bx '
0&
x%
x$
x#
0"
x!
$end
#3
1&
#5
b0 (
0!
b0 '
1"
#6
1$
1#
1%
0&
#10
0"
#15
b1 (
1"
#20
0"
#25
b101 '
1"
#30
0"
#35
b1010 '
1"
#40
0"
#45
b1111 '
1"
#50
0"
#55
b10100 '
1"
#60
0"
#65
b11001 '
1"
#70
0"
#75
b11110 '
1"
#80
0"
#85
b10 (
b0 '
1"
#90
0"
#95
b0 (
1!
1"
#100
0"
#105
b1 (
1"
#110
0"
#115
b101 '
1"
#120
0"
#125
b1010 '
1"
#130
0"
#135
b1111 '
1"
#140
0"
#145
b10100 '
1"
#150
0"
#155
b11001 '
1"
#160
0"
#165
b11110 '
1"
#170
0"
#175
b10 (
b0 '
1"
#180
0"
#185
b0 (
1"
#190
0"
#195
b1 (
1"
#200
0"
#205
b101 '
1"
