OneDrive/Desktop/75/week_7/src/n_adder/gray_code1.v
module gray_code1#(
    parameter bit=16
)(
    output reg [bit-1:0]bin,
    input wire clk,
    input wire rst,
    output wire [bit-1:0]gray

);
always @(posedge clk) begin
    if (rst==1) begin
        bin <= {bit{1'b0}};
    end
    else begin 
        bin <= bin+ {bit{1'b1}};
    end
end

    assign gray = bin ^ (bin >> 1);
endmodule


//this will work independ

OneDrive/Desktop/75/week_7/src/n_adder/tb_gray_code_copy.v
module tb_gray_code_copy;
    localparam bit =16;
    reg clk;
    wire [bit-1:0]bin;
    reg rst;
    wire [bit-1:0]gray;

    gray_code1 #(
        .bit(bit)
    ) uut(
        .clk(clk), .rst(rst), .bin(bin), .gray(gray)
    );
    always #5 clk=~clk;
    initial begin
        $dumpfile("dump.vcd");
        $dumpvars(0,tb_gray_code_copy);
        rst=0;clk=0;#2;
        rst=1;#5;
        rst=0;#150;
        $finish;
    end
endmodule

OneDrive/Desktop/75/week_7/src/n_adder/dump.vcd
$date
	Tue Jun 30 14:02:07 2026
$end
$version
	Icarus Verilog
$end
$timescale
	1s
$end
$scope module tb_gray_code_copy $end
$var wire 16 ! gray [15:0] $end
$var wire 16 " bin [15:0] $end
$var reg 1 # clk $end
$var reg 1 $ rst $end
$scope module uut $end
$var wire 1 # clk $end
$var wire 16 % gray [15:0] $end
$var wire 1 $ rst $end
$var reg 16 & bin [15:0] $end
$upscope $end
$upscope $end
$enddefinitions $end
#0
$dumpvars
bx &
bx %
0$
0#
bx "
bx !
$end
#2
1$
#5
b0 !
b0 %
b0 "
b0 &
1#
#7
0$
#10
0#
#15
b1000000000000000 !
b1000000000000000 %
b1111111111111111 "
b1111111111111111 &
1#
#20
0#
#25
b1000000000000001 !
b1000000000000001 %
b1111111111111110 "
b1111111111111110 &
1#
#30
0#
#35
b1000000000000011 !
b1000000000000011 %
b1111111111111101 "
b1111111111111101 &
1#
#40
0#
#45
b1000000000000010 !
b1000000000000010 %
b1111111111111100 "
b1111111111111100 &
1#
#50
0#
#55
b1000000000000110 !
b1000000000000110 %
b1111111111111011 "
b1111111111111011 &
1#
#60
0#
#65
b1000000000000111 !
b1000000000000111 %
b1111111111111010 "
b1111111111111010 &
1#
#70
0#
#75
b1000000000000101 !
b1000000000000101 %
b1111111111111001 "
b1111111111111001 &
1#
#80
0#
#85
b1000000000000100 !
b1000000000000100 %
b1111111111111000 "
b1111111111111000 &
1#
#90
0#
#95
b1000000000001100 !
b1000000000001100 %
b1111111111110111 "
b1111111111110111 &
1#
#100
0#
#105
b1000000000001101 !
b1000000000001101 %
b1111111111110110 "
b1111111111110110 &
1#
#110
0#
#115
b1000000000001111 !
b1000000000001111 %
b1111111111110101 "
b1111111111110101 &
1#
#120
0#
#125
b1000000000001110 !
b1000000000001110 %
b1111111111110100 "
b1111111111110100 &
1#
#130
0#
#135
b1000000000001010 !
b1000000000001010 %
b1111111111110011 "
b1111111111110011 &
1#
#140
0#
#145
b1000000000001011 !
b1000000000001011 %
b1111111111110010 "
b1111111111110010 &
1#
#150
0#
#155
b1000000000001001 !
b1000000000001001 %
b1111111111110001 "
b1111111111110001 &
1#
