OneDrive/Desktop/75/week_2/full_adder/or_gate.v

module or_gate(
    input a,
    input b,
    output y
);

    assign y = a||b;
endmodule

OneDrive/Desktop/75/week_2/full_adder/half_adder.v
module half_adder(
    input wire a,
    input wire b,
    output wire carry,
    output wire sum
);
    assign sum=a^b;
    assign carry =a&b;
endmodule

OneDrive/Desktop/75/week_2/n_bitadder/full_adder.v
module full_adder(
    input wire a,
    input wire b,
    input wire cin,
    output wire sum,
    output wire cout
);

    // Internal wires to connect the chips together
    wire sum1;
    wire carry1;
    wire carry2;

    // Instantiate First Half Adder
    half_adder HA1 (
        .a(a), 
        .b(b), 
        .sum(sum1), 
        .carry(carry1)
    );

    // Instantiate Second Half Adder
    half_adder HA2 (
        .a(sum1), 
        .b(cin), 
        .sum(sum), 
        .carry(carry2)
    );

    // Instantiate OR Gate for the final carry
    or_gate OR1 (
        .a(carry1), 
        .b(carry2), 
        .y(cout)
    );

endmodule

OneDrive/Desktop/75/week_2/n_bitadder/ripple_carry_nbit.v
module ripple_carry_nbit(
    input wire [n-1:0] A,
    input wire [n-1:0] B,
    input wire cin,
    output wire [n-1:0] sum,
    output wire cout
);
    parameter n=8;
    wire [n:0]carry;
    assign carry[0]=cin;
    genvar i;
    generate 

        for(i = 0; i < n; i = i + 1) begin :adder_loop
            full_adder FAN (.a(A[i]), .b(B[i]), .cin(carry[i]), .sum(sum[i]), .cout(carry[i+1]));
        end
        assign cout=carry[n];
    endgenerate
endmodule

OneDrive/Desktop/75/week_2/n_bitadder/tb_n_bit.v

module tb_nbit;
    parameter n=8;

    reg [n-1:0] A;
    reg [n-1:0] B;
    reg cin; 
    wire [n-1:0] sum;
    wire cout;
    ripple_carry_nbit uut (
        .A(A), 
        .B(B), 
        .cin(cin), 
        .sum(sum), 
        .cout(cout)
    );
    integer i;
    initial begin
        $dumpfile("dump.vcd");
        $dumpvars(0, tb_nbit);
        for(i = 0; i < 10; i = i + 1) begin
            A = $random;
            B= $random;
            cin= $random % 2;
            #10;
            end
        $finish;
    end
endmodule

OneDrive/Desktop/75/week_2/n_bitadder/dump.vcd
$date
	Fri May 29 21:59:53 2026
$end
$version
	Icarus Verilog
$end
$timescale
	1s
$end
$scope module tb_nbit $end
$var wire 8 ! sum [7:0] $end
$var wire 1 " cout $end
$var reg 8 # A [7:0] $end
$var reg 8 $ B [7:0] $end
$var reg 1 % cin $end
$var integer 32 & i [31:0] $end
$scope module uut $end
$var wire 8 ' A [7:0] $end
$var wire 8 ( B [7:0] $end
$var wire 1 % cin $end
$var wire 8 ) sum [7:0] $end
$var wire 1 " cout $end
$var wire 9 * carry [8:0] $end
$scope begin adder_loop[0] $end
$scope module FAN $end
$var wire 1 + a $end
$var wire 1 , b $end
$var wire 1 - cin $end
$var wire 1 . sum1 $end
$var wire 1 / sum $end
$var wire 1 0 cout $end
$var wire 1 1 carry2 $end
$var wire 1 2 carry1 $end
$scope module HA1 $end
$var wire 1 + a $end
$var wire 1 , b $end
$var wire 1 2 carry $end
$var wire 1 . sum $end
$upscope $end
$scope module HA2 $end
$var wire 1 . a $end
$var wire 1 - b $end
$var wire 1 1 carry $end
$var wire 1 / sum $end
$upscope $end
$scope module OR1 $end
$var wire 1 2 a $end
$var wire 1 1 b $end
$var wire 1 0 y $end
$upscope $end
$upscope $end
$upscope $end
$scope begin adder_loop[1] $end
$scope module FAN $end
$var wire 1 3 a $end
$var wire 1 4 b $end
$var wire 1 5 cin $end
$var wire 1 6 sum1 $end
$var wire 1 7 sum $end
$var wire 1 8 cout $end
$var wire 1 9 carry2 $end
$var wire 1 : carry1 $end
$scope module HA1 $end
$var wire 1 3 a $end
$var wire 1 4 b $end
$var wire 1 : carry $end
$var wire 1 6 sum $end
$upscope $end
$scope module HA2 $end
$var wire 1 6 a $end
$var wire 1 5 b $end
$var wire 1 9 carry $end
$var wire 1 7 sum $end
$upscope $end
$scope module OR1 $end
$var wire 1 : a $end
$var wire 1 9 b $end
$var wire 1 8 y $end
$upscope $end
$upscope $end
$upscope $end
$scope begin adder_loop[2] $end
$scope module FAN $end
$var wire 1 ; a $end
$var wire 1 < b $end
$var wire 1 = cin $end
$var wire 1 > sum1 $end
$var wire 1 ? sum $end
$var wire 1 @ cout $end
$var wire 1 A carry2 $end
$var wire 1 B carry1 $end
$scope module HA1 $end
$var wire 1 ; a $end
$var wire 1 < b $end
$var wire 1 B carry $end
$var wire 1 > sum $end
$upscope $end
$scope module HA2 $end
$var wire 1 > a $end
$var wire 1 = b $end
$var wire 1 A carry $end
$var wire 1 ? sum $end
$upscope $end
$scope module OR1 $end
$var wire 1 B a $end
$var wire 1 A b $end
$var wire 1 @ y $end
$upscope $end
$upscope $end
$upscope $end
$scope begin adder_loop[3] $end
$scope module FAN $end
$var wire 1 C a $end
$var wire 1 D b $end
$var wire 1 E cin $end
$var wire 1 F sum1 $end
$var wire 1 G sum $end
$var wire 1 H cout $end
$var wire 1 I carry2 $end
$var wire 1 J carry1 $end
$scope module HA1 $end
$var wire 1 C a $end
$var wire 1 D b $end
$var wire 1 J carry $end
$var wire 1 F sum $end
$upscope $end
$scope module HA2 $end
$var wire 1 F a $end
$var wire 1 E b $end
$var wire 1 I carry $end
$var wire 1 G sum $end
$upscope $end
$scope module OR1 $end
$var wire 1 J a $end
$var wire 1 I b $end
$var wire 1 H y $end
$upscope $end
$upscope $end
$upscope $end
$scope begin adder_loop[4] $end
$scope module FAN $end
$var wire 1 K a $end
$var wire 1 L b $end
$var wire 1 M cin $end
$var wire 1 N sum1 $end
$var wire 1 O sum $end
$var wire 1 P cout $end
$var wire 1 Q carry2 $end
$var wire 1 R carry1 $end
$scope module HA1 $end
$var wire 1 K a $end
$var wire 1 L b $end
$var wire 1 R carry $end
$var wire 1 N sum $end
$upscope $end
$scope module HA2 $end
$var wire 1 N a $end
$var wire 1 M b $end
$var wire 1 Q carry $end
$var wire 1 O sum $end
$upscope $end
$scope module OR1 $end
$var wire 1 R a $end
$var wire 1 Q b $end
$var wire 1 P y $end
$upscope $end
$upscope $end
$upscope $end
$scope begin adder_loop[5] $end
$scope module FAN $end
$var wire 1 S a $end
$var wire 1 T b $end
$var wire 1 U cin $end
$var wire 1 V sum1 $end
$var wire 1 W sum $end
$var wire 1 X cout $end
$var wire 1 Y carry2 $end
$var wire 1 Z carry1 $end
$scope module HA1 $end
$var wire 1 S a $end
$var wire 1 T b $end
$var wire 1 Z carry $end
$var wire 1 V sum $end
$upscope $end
$scope module HA2 $end
$var wire 1 V a $end
$var wire 1 U b $end
$var wire 1 Y carry $end
$var wire 1 W sum $end
$upscope $end
$scope module OR1 $end
$var wire 1 Z a $end
$var wire 1 Y b $end
$var wire 1 X y $end
$upscope $end
$upscope $end
$upscope $end
$scope begin adder_loop[6] $end
$scope module FAN $end
$var wire 1 [ a $end
$var wire 1 \ b $end
$var wire 1 ] cin $end
$var wire 1 ^ sum1 $end
$var wire 1 _ sum $end
$var wire 1 ` cout $end
$var wire 1 a carry2 $end
$var wire 1 b carry1 $end
$scope module HA1 $end
$var wire 1 [ a $end
$var wire 1 \ b $end
$var wire 1 b carry $end
$var wire 1 ^ sum $end
$upscope $end
$scope module HA2 $end
$var wire 1 ^ a $end
$var wire 1 ] b $end
$var wire 1 a carry $end
$var wire 1 _ sum $end
$upscope $end
$scope module OR1 $end
$var wire 1 b a $end
$var wire 1 a b $end
$var wire 1 ` y $end
$upscope $end
$upscope $end
$upscope $end
$scope begin adder_loop[7] $end
$scope module FAN $end
$var wire 1 c a $end
$var wire 1 d b $end
$var wire 1 e cin $end
$var wire 1 f sum1 $end
$var wire 1 g sum $end
$var wire 1 h cout $end
$var wire 1 i carry2 $end
$var wire 1 j carry1 $end
$scope module HA1 $end
$var wire 1 c a $end
$var wire 1 d b $end
$var wire 1 j carry $end
$var wire 1 f sum $end
$upscope $end
$scope module HA2 $end
$var wire 1 f a $end
$var wire 1 e b $end
$var wire 1 i carry $end
$var wire 1 g sum $end
$upscope $end
$scope module OR1 $end
$var wire 1 j a $end
$var wire 1 i b $end
$var wire 1 h y $end
$upscope $end
$upscope $end
$upscope $end
$upscope $end
$upscope $end
$enddefinitions $end
#0
$dumpvars
0j
0i
0h
1g
1f
0e
1d
0c
0b
0a
0`
0_
0^
0]
0\
0[
0Z
0Y
0X
1W
1V
0U
0T
1S
0R
0Q
0P
0O
0N
0M
0L
0K
0J
0I
0H
0G
0F
0E
0D
0C
0B
0A
0@
1?
1>
0=
0<
1;
0:
09
08
17
06
15
04
03
02
11
10
0/
1.
1-
1,
0+
b11 *
b10100110 )
b10000001 (
b100100 '
b0 &
1%
b10000001 $
b100100 #
0"
b10100110 !
$end
#10
1O
1M
1H
1I
1E
1@
0?
1A
1=
b11111 *
18
0G
0g
1/
01
07
19
b1110001 !
b1110001 )
1_
1F
0f
0.
12
16
1^
1<
1D
0d
1+
13
0;
1[
b1101 $
b1101 (
b1100011 #
b1100011 '
b1 &
#20
0g
0e
1E
0`
1@
1_
0a
0?
1A
0]
1=
0X
18
1W
0Y
07
19
0M
0U
15
0H
0P
0/
11
b1111 *
10
1G
0I
b1111000 !
b1111000 )
1O
0Q
1.
02
0F
1N
0,
14
0<
0D
1L
03
1;
b10010 $
b10010 (
b1100101 #
b1100101 '
b10 &
#30
1g
1e
1`
0_
1a
1]
1X
0W
1Y
1U
1P
0O
1Q
1M
b11111111 *
1H
1?
0A
b10000100 !
b10000100 )
0G
1I
0>
1B
1F
1<
1T
1\
1C
0S
0[
b1110110 $
b1110110 (
b1101 #
b1101 '
b11 &
#40
0g
0e
0`
1_
0a
0]
0X
0?
1W
0Y
0=
0U
08
0P
1"
17
09
1G
0I
b1111010 !
b1111010 )
1O
0Q
b100011011 *
1h
06
0F
1J
0N
1j
04
1D
0L
0T
0\
1d
1S
1[
1c
b10001100 $
b10001100 (
b11101101 #
b11101101 '
b100 &
#50
0?
1g
0=
0O
05
1e
08
0M
00
0_
1`
17
09
0H
0W
b10001011 !
b10001011 )
1/
01
0^
1b
16
0J
0V
0-
1,
0D
1\
0+
13
0C
0S
b110001000 *
0%
b11000101 $
b11000101 (
b11000110 #
b11000110 '
b101 &
#60
1?
1=
18
07
19
1_
1"
15
1]
1O
0g
1i
1h
b1011100 !
b1011100 )
0/
10
b111001110 *
1X
1N
1f
0j
0.
12
1Z
14
1L
1T
0d
1+
03
1S
b1110111 $
b1110111 (
b11100101 #
b11100101 '
b110 &
#70
1Y
1U
1P
0O
1Q
1M
05
1E
1H
1]
1e
1/
00
0?
1A
1@
1g
0i
07
09
0G
1I
0W
1X
b10000001 !
b10000001 )
0_
1a
b111111100 *
1`
1.
02
1>
0B
0f
1j
06
1:
1F
1V
0Z
1^
0b
0,
0<
1d
13
1C
0S
0[
b11110010 $
b11110010 (
b10001111 #
b10001111 '
b111 &
#80
0M
0H
0]
1G
0I
0X
0E
1W
0Y
0@
0U
1?
0A
0P
0=
0O
0Q
b110000000 *
08
b10101101 !
b10101101 )
0_
0a
0N
0:
0^
1b
1,
04
1<
0L
0T
0+
03
0;
1S
1[
b11000101 $
b11000101 (
b11101000 #
b11101000 '
b1000 &
#90
1U
1P
1Q
1_
17
1M
1]
0"
15
1E
0e
1G
1H
1W
1X
1g
0i
0h
10
0?
1@
b11101011 !
b11101011 )
0O
0`
0F
1J
0V
1Z
1f
0j
0.
12
0>
1B
1N
0b
1-
1D
1T
0\
0d
1+
1;
1K
0[
b1111011 *
1%
b101101 $
b101101 (
b10111101 #
b10111101 '
b1001 &
#100
b1010 &
