OneDrive/Desktop/75/week_8/src/uart_fsm/uart.v
module uart #(
    //brg-baud rate generator
    parameter clk_freq=50000000,
    parameter baud_rate=9600,
    parameter DIVISOR=5208
)(
    input wire rst,
    input wire clk, 
    output reg tx_active,
    input wire tx_start,
    output reg tx_done,
    input wire [7:0]tx_data,
    output reg tx_out
);
reg [12:0]baud_count;
wire baud_tick;
reg [1:0]st;
reg [7:0]tx_shift;
reg [3:0]index;
localparam idle=2'b00;
localparam start=2'b01;
localparam data=2'b10;
localparam stop=2'b11;

assign baud_tick=(baud_count==(DIVISOR-1));
always @(posedge clk) begin
    if(rst) begin
        baud_count<=13'd0;
    end
    else if(tx_active)begin
        if(baud_tick)begin
            baud_count<=13'd0;
        end
        else begin
            baud_count<=baud_count+13'd1;
        end
    end
    else begin
        baud_count<=13'd0;
    end
end
always @(posedge clk) begin
    if(rst)begin
        st<=idle;
        index<=4'd0;
        tx_shift<=8'd0;
        tx_active<=0;
        tx_done<=0;
        tx_out<=0;
    end
    else begin
        case (st)
            idle:begin
                tx_out<=1'b1;
                tx_done<=0;
                if(tx_start)begin
                    tx_active<=1;
                    tx_shift<=tx_data;
                    st<=start;
                end
            end
            start:begin
                tx_out<=0;
                if(baud_tick)begin
                    st<=data;
                    index<=4'd0;
                end
            end
            data:begin
                tx_out<=tx_shift[0];
                if(baud_tick)begin
                    if(index==4'd7)begin
                        st<=stop;
                    end
                    else begin
                        index<=index+4'd1;
                        tx_shift<={1'b1,tx_shift[7:1]};
                    end
                end
            end
            stop:begin
                tx_done<=1;
                tx_out<=1;
                if(baud_tick)begin
                    tx_active=1'b0;
                    tx_done=1'b0;
                    st<=idle;
                end
            end
            default:st<=idle;
        endcase
    end
end
endmodule

//total 8 bits are there so we need to index them from msb to lsb-----index is used

OneDrive/Desktop/75/week_8/src/parity/tb_uart.v
`timescale 1ns/1ps
module tb_uart;
    reg tx_start;
    reg [7:0]tx_data;
    wire tx_done;
    wire tx_active ;
    wire tx_out ;
    reg rst;
    reg clk;
    uart uut(
        .clk(clk), .rst(rst), .tx_done(tx_done), .tx_out(tx_out), .tx_active(tx_active), .tx_start(tx_start), .tx_data(tx_data)
    );
    always #10 clk=~clk;   //so thime period will be 20ns ,so freq will be 50Mhz
    initial begin
        $dumpfile("dump.vcd");
        $dumpvars(0,tb_uart);
        rst=0;clk=0;#20;
        rst=1;#20;
        rst=0;#20;
        tx_data=01010101;tx_start=1;#1000;
        $finish;
    end
endmodule

OneDrive/Desktop/75/week_8/src/uart_fsm/dump.vcd
$date
	Sat Jul 04 01:50:20 2026
$end
$version
	Icarus Verilog
$end
$timescale
	1ps
$end
$scope module tb_uart $end
$var wire 1 ! tx_out $end
$var wire 1 " tx_done $end
$var wire 1 # tx_active $end
$var reg 1 $ clk $end
$var reg 1 % rst $end
$var reg 8 & tx_data [7:0] $end
$var reg 1 ' tx_start $end
$scope module uut $end
$var wire 1 $ clk $end
$var wire 1 % rst $end
$var wire 8 ( tx_data [7:0] $end
$var wire 1 ' tx_start $end
$var wire 1 ) baud_tick $end
$var reg 13 * baud_count [12:0] $end
$var reg 4 + index [3:0] $end
$var reg 2 , st [1:0] $end
$var reg 1 # tx_active $end
$var reg 1 " tx_done $end
$var reg 1 ! tx_out $end
$var reg 8 - tx_shift [7:0] $end
$upscope $end
$upscope $end
$enddefinitions $end
#0
$dumpvars
bx -
bx ,
bx +
bx *
x)
bx (
x'
bx &
0%
0$
x#
x"
x!
$end
#10000
0)
b0 *
b0 ,
1$
#20000
0$
1%
#30000
0!
0"
0#
b0 -
b0 +
1$
#40000
0$
0%
#50000
1!
1$
#60000
0$
1'
b10110101 &
b10110101 (
#70000
b1 ,
b10110101 -
1#
1$
#80000
0$
#90000
b1 *
0!
1$
#100000
0$
#110000
b10 *
1$
#120000
0$
#130000
b11 *
1$
#140000
0$
#150000
b100 *
1$
#160000
0$
#170000
b101 *
1$
#180000
0$
#190000
b110 *
1$
#200000
0$
#210000
b111 *
1$
#220000
0$
#230000
b1000 *
1$
#240000
0$
#250000
b1001 *
1$
#260000
0$
#270000
b1010 *
1$
#280000
0$
#290000
b1011 *
1$
#300000
0$
#310000
b1100 *
1$
#320000
0$
#330000
b1101 *
1$
#340000
0$
#350000
b1110 *
1$
#360000
0$
#370000
b1111 *
1$
#380000
0$
#390000
b10000 *
1$
#400000
0$
#410000
b10001 *
1$
#420000
0$
#430000
b10010 *
1$
#440000
0$
#450000
b10011 *
1$
#460000
0$
#470000
b10100 *
1$
#480000
0$
#490000
b10101 *
1$
#500000
0$
#510000
b10110 *
1$
#520000
0$
#530000
b10111 *
1$
#540000
0$
#550000
b11000 *
1$
#560000
0$
#570000
b11001 *
1$
#580000
0$
#590000
b11010 *
1$
#600000
0$
#610000
b11011 *
1$
#620000
0$
#630000
b11100 *
1$
#640000
0$
#650000
b11101 *
1$
#660000
0$
#670000
b11110 *
1$
#680000
0$
#690000
b11111 *
1$
#700000
0$
#710000
b100000 *
1$
#720000
0$
#730000
b100001 *
1$
#740000
0$
#750000
b100010 *
1$
#760000
0$
#770000
b100011 *
1$
#780000
0$
#790000
b100100 *
1$
#800000
0$
#810000
b100101 *
1$
#820000
0$
#830000
b100110 *
1$
#840000
0$
#850000
b100111 *
1$
#860000
0$
#870000
b101000 *
1$
#880000
0$
#890000
b101001 *
1$
#900000
0$
#910000
b101010 *
1$
#920000
0$
#930000
b101011 *
1$
#940000
0$
#950000
b101100 *
1$
#960000
0$
#970000
b101101 *
1$
#980000
0$
#990000
b101110 *
1$
#1000000
0$
#1010000
b101111 *
1$
#1020000
0$
#1030000
b110000 *
1$
#1040000
0$
#1050000
b110001 *
1$
