OneDrive/Desktop/75/week_3/src/8bit_flipflop/bit_flipflop.v
module bit_flipflop(
    input wire rst,
    input wire clk,
    input wire serial_in,
    output wire serial_out
    
);
reg [7:0]shift_reg;
assign serial_out=shift_reg[7];
always @(posedge clk) begin
    if(rst==1'b1) begin
        shift_reg <= 8'b00000000;
    end else begin
        shift_reg<={shift_reg[6:0],serial_in};
    end
end
endmodule

OneDrive/Desktop/75/week_3/src/8bit_flipflop/tb_bit_flipflop.v
module tb_bit_flipflop;
    reg clk;
    reg rst;
    wire serial_out;
    reg serial_in;
    
    bit_flipflop uut(
        .clk(clk),
        .rst(rst),
        .serial_in(serial_in),
        .serial_out(serial_out)
    );
    always #5 clk=~clk;
    initial begin
        $dumpfile("dump.vcd");
        $dumpvars(0,tb_bit_flipflop);
        clk=0;rst=0;serial_in=0;
        #2;
        rst=1;
        #2;
        rst=0;
        #6;
        serial_in = 1; #10; // Cycle 1 (Target bit: 1)
        serial_in = 0; #10; // Cycle 2 (Target bit: 0)
        serial_in = 1; #10; // Cycle 3 (Target bit: 1)
        serial_in = 1; #10; // Cycle 4 (Target bit: 1)
        serial_in = 0; #10; // Cycle 5 (Target bit: 0)
        serial_in = 1; #10; // Cycle 6 (Target bit: 1)
        serial_in = 0; #10; // Cycle 7 (Target bit: 0)
        serial_in = 0; #10; // Cycle 8 (Target bit: 0)

        // Stop feeding data, just feed 0s and let the clock run
        serial_in = 0;
        #50;

        $finish;
    end
endmodule

OneDrive/Desktop/75/week_3/src/8bit_flipflop/dump.vcd
$date
	Wed Jun 03 22:40:30 2026
$end
$version
	Icarus Verilog
$end
$timescale
	1s
$end
$scope module tb_bit_flipflop $end
$var wire 1 ! serial_out $end
$var reg 1 " clk $end
$var reg 1 # rst $end
$var reg 1 $ serial_in $end
$scope module uut $end
$var wire 1 " clk $end
$var wire 1 # rst $end
$var wire 1 $ serial_in $end
$var wire 1 ! serial_out $end
$var reg 8 % shift_reg [7:0] $end
$upscope $end
$upscope $end
$enddefinitions $end
#0
$dumpvars
bx %
0$
0#
0"
x!
$end
#2
1#
#4
0#
#5
bx0 %
1"
#10
0"
1$
#15
bx01 %
1"
#20
0"
0$
#25
bx010 %
1"
#30
0"
1$
#35
bx0101 %
1"
#40
0"
#45
bx01011 %
1"
#50
0"
0$
#55
bx010110 %
1"
#60
0"
1$
#65
bx0101101 %
1"
#70
0"
0$
#75
0!
b1011010 %
1"
#80
0"
#85
1!
b10110100 %
1"
#90
0"
#95
0!
b1101000 %
1"
#100
0"
#105
1!
b11010000 %
1"
#110
0"
#115
b10100000 %
1"
#120
0"
#125
0!
b1000000 %
1"
#130
0"
#135
1!
b10000000 %
1"
