OneDrive/Desktop/75/week_9/src/baud_gen/rx_baud_gen.v
module rx_baud_gen (
    input wire clk,
    input wire rst,
    output wire baud_tick
);

reg [8:0] baud_count;
assign baud_tick = (baud_count == 9'd325);

always @(posedge clk) begin
    if (rst) begin
        baud_count <= 9'd0;
    end
    else if (baud_tick) begin
        baud_count <= 9'd0;
    end
    else begin
        baud_count <= baud_count + 9'd1;
    end
end
endmodule

OneDrive/Desktop/75/week_9/src/baud_gen/tb_baud.v
module tb_baud;
    reg clk;
    reg rst;
    wire baud_tick;
    rx_baud_gen uut(
        .clk(clk), .rst(rst), .baud_tick(baud_tick)
    );
    always #10 clk=~clk;
    initial begin 
        $dumpfile("dump.vcd");
        $dumpvars(0,tb_baud);
        rst=0;clk=0;#10;
        rst=1;
        #10;
        rst=0;
        #1000;
        $finish;
    end
endmodule

OneDrive/Desktop/75/week_9/src/baud_gen/dump.vcd
$date
	Tue Jul 07 16:31:52 2026
$end
$version
	Icarus Verilog
$end
$timescale
	1s
$end
$scope module tb_baud $end
$var wire 1 ! baud_tick $end
$var reg 1 " clk $end
$var reg 1 # rst $end
$scope module uut $end
$var wire 1 " clk $end
$var wire 1 # rst $end
$var wire 1 ! baud_tick $end
$var reg 9 $ baud_count [8:0] $end
$upscope $end
$upscope $end
$enddefinitions $end
#0
$dumpvars
bx $
0#
0"
x!
$end
#10
0!
b0 $
1#
1"
#20
0#
0"
#30
b1 $
1"
#40
0"
#50
b10 $
1"
#60
0"
#70
b11 $
1"
#80
0"
#90
b100 $
1"
#100
0"
#110
b101 $
1"
#120
0"
#130
b110 $
1"
#140
0"
#150
b111 $
1"
#160
0"
#170
b1000 $
1"
#180
0"
#190
b1001 $
1"
#200
0"
#210
b1010 $
1"
#220
0"
#230
b1011 $
1"
#240
0"
#250
b1100 $
1"
#260
0"
#270
b1101 $
1"
#280
0"
#290
b1110 $
1"
#300
0"
#310
b1111 $
1"
#320
0"
#330
b10000 $
1"
#340
0"
#350
b10001 $
1"
#360
0"
#370
b10010 $
1"
#380
0"
#390
b10011 $
1"
#400
0"
#410
b10100 $
1"
#420
0"
#430
b10101 $
1"
#440
0"
#450
b10110 $
1"
#460
0"
#470
b10111 $
1"
#480
0"
#490
b11000 $
1"
#500
0"
#510
b11001 $
1"
#520
0"
#530
b11010 $
1"
#540
0"
#550
b11011 $
1"
#560
0"
#570
b11100 $
1"
#580
0"
#590
b11101 $
1"
#600
0"
#610
b11110 $
1"
#620
0"
#630
b11111 $
1"
#640
0"
#650
b100000 $
1"
#660
0"
#670
b100001 $
1"
#680
0"
#690
b100010 $
1"
#700
0"
#710
b100011 $
1"
#720
0"
#730
b100100 $
1"
#740
0"
#750
b100101 $
1"
#760
0"
#770
b100110 $
1"
#780
0"
#790
b100111 $
1"
#800
0"
#810
b101000 $
1"
#820
0"
#830
b101001 $
1"
#840
0"
#850
b101010 $
1"
#860
0"
#870
b101011 $
1"
#880
0"
#890
b101100 $
1"
#900
0"
#910
b101101 $
1"
#920
0"
#930
b101110 $
1"
#940
0"
#950
b101111 $
1"
#960
0"
#970
b110000 $
1"
#980
0"
#990
b110001 $
1"
#1000
0"
#1010
b110010 $
1"
