OneDrive/Desktop/75/week 1/src/full_adder/full_adder.v

module full_adder(
    input wire carryint,
    input wire sum,
    output wire sumout,
    output wire carryout

);
    assign sumout= sum;
    assign carryout=carryint;
endmodule

OneDrive/Desktop/75/week 1/src/full_adder/half_add.v
module half_add(
    input wire a,
    input wire b,
    input wire carryin,
    output wire carryint,
    output wire sum
);
    assign sum=a^b || carryin;
    assign carryint =a&b;
endmodule

OneDrive/Desktop/75/week 1/src/full_adder/tb_full_adder.v
module tb_full_adder;
    reg a;
    reg b;
    reg carryin;
    wire sum;
    wire carryint;
    wire carryout;
    wire sumout;
    half_add uut1(
        .a(a), .b(b), .carryin(carryin), .sum(sum), .carryint(carryint)
    );
    full_adder uut2(
        .sum(sum), .carryint(carryint), .carryout(carryout), .sumout(sumout)
    );
    initial begin
        $dumpfile("dump.vcd");
        $dumpvars(0,tb_full_adder);
        a=0;b=0;carryin=0; #10
        a=0;b=0;carryin=1; #10
        a=0;b=1;carryin=0; #10
        a=0;b=1;carryin=1; #10
        a=1;b=0;carryin=0; #10
        a=1;b=0;carryin=1; #10
        a=1;b=1;carryin=0; #10
        a=1;b=1;carryin=1; #10
        $finish;
    end
endmodule

OneDrive/Desktop/75/week 1/src/full_adder/dump.vcd
$date
	Fri May 22 21:37:14 2026
$end
$version
	Icarus Verilog
$end
$timescale
	1s
$end
$scope module tb_full_adder $end
$var wire 1 ! sumout $end
$var wire 1 " sum $end
$var wire 1 # carryout $end
$var wire 1 $ carryint $end
$var reg 1 % a $end
$var reg 1 & b $end
$var reg 1 ' carryin $end
$scope module uut1 $end
$var wire 1 % a $end
$var wire 1 & b $end
$var wire 1 ' carryin $end
$var wire 1 $ carryint $end
$var wire 1 " sum $end
$upscope $end
$scope module uut2 $end
$var wire 1 $ carryint $end
$var wire 1 # carryout $end
$var wire 1 " sum $end
$var wire 1 ! sumout $end
$upscope $end
$upscope $end
$enddefinitions $end
#0
$dumpvars
0'
0&
0%
0$
0#
0"
0!
$end
#10
1!
1"
1'
#20
0'
1&
#30
1'
#40
0'
0&
1%
#50
1'
#60
0!
0"
1#
1$
0'
1&
#70
1!
1"
1'
