OneDrive/Desktop/75/week_4/src/gray_code/gray_code.v
module gray_code(
    input wire [3:0]bin,
    input wire clk,
    input wire rst,
    output reg [3:0]gray

);
always @(posedge clk) begin
    if (rst==1) begin
        gray<=4'b0000;
    end
    else begin
        gray = bin ^ (bin >> 1);
    end
end
endmodule
//here gray will depend on the bin so to avoid this we can put bin<= bin+1; 
//inside the clk and wire--->reg

OneDrive/Desktop/75/week_4/src/gray_code/tb_gray_code.v
module tb_gray_code;
    reg clk;
    reg [3:0]bin;
    reg rst;
    wire [3:0]gray;

    gray_code uut(
        .clk(clk), .rst(rst), .bin(bin), .gray(gray)
    );
    always #5 clk=~clk;
    initial begin
        $dumpfile("dump.vcd");
        $dumpvars(0,tb_gray_code);
        rst=0;clk=0;#2;
        rst=1;#5;
        rst=0;bin=4'b0101;#15;
        bin=4'b1111;#5;
        bin=4'b0101;#5;
        $finish;
    end
endmodule

OneDrive/Desktop/75/week_4/src/gray_code/dump.vcd
$date
	Wed Jun 10 15:41:04 2026
$end
$version
	Icarus Verilog
$end
$timescale
	1s
$end
$scope module tb_gray_code $end
$var wire 4 ! gray [3:0] $end
$var reg 4 " bin [3:0] $end
$var reg 1 # clk $end
$var reg 1 $ rst $end
$scope module uut $end
$var wire 4 % bin [3:0] $end
$var wire 1 # clk $end
$var wire 1 $ rst $end
$var reg 4 & gray [3:0] $end
$upscope $end
$upscope $end
$enddefinitions $end
#0
$dumpvars
bx &
bx %
0$
0#
bx "
bx !
$end
#2
1$
#5
b0 !
b0 &
1#
#7
b101 "
b101 %
0$
#10
0#
#15
b111 !
b111 &
1#
#20
0#
#22
b1111 "
b1111 %
#25
b1000 !
b1000 &
1#
#27
b101 "
b101 %
