OneDrive/Desktop/75/week_4/src/tue_code/counter_nbit.v
module counter_nbit(
    input wire rst,
    input wire clk,
    output reg [12:0]q

);
always @(posedge clk) begin
    if(rst==1) begin
        q<=13'd0;
    end
    else if(q==13'd5208) begin
        q<=13'd0;
    end
    else begin
        q<=q+13'd1;
    end
    
end
endmodule
//	Modulo-6 counter: reset at count==5 (not 6!). Modulo-10 counter. 
//Modulo-5208 counter (your future UART baud generator). Verify each resets at exactly the right value. Off-by-one is a real and common bug here.
//for 5208 13 bits needed

OneDrive/Desktop/75/week_4/src/tue_code/tb_counter_nbit.v
module tb_counter_nbit;
    reg rst;
    reg clk;
    wire [12:0]q;
    counter_nbit uut(
    .clk(clk), 
    .rst(rst),
    .q(q)
    );
    always #5 clk=~clk;
    initial begin
        $dumpfile("dump.vcd");
        $dumpvars(0,tb_counter_nbit);
        rst=0;clk=0;#200
        rst=1;
        #60;
        rst=0;#1200
        $finish;
    end
endmodule

OneDrive/Desktop/75/week_4/src/tue_code/dump.vcd
$date
	Tue Jun 09 00:52:57 2026
$end
$version
	Icarus Verilog
$end
$timescale
	1s
$end
$scope module tb_counter_nbit $end
$var wire 13 ! q [12:0] $end
$var reg 1 " clk $end
$var reg 1 # rst $end
$scope module uut $end
$var wire 1 " clk $end
$var wire 1 # rst $end
$var reg 13 $ q [12:0] $end
$upscope $end
$upscope $end
$enddefinitions $end
#0
$dumpvars
bx $
0#
0"
bx !
$end
#5
1"
#10
0"
#15
1"
#20
0"
#25
1"
#30
0"
#35
1"
#40
0"
#45
1"
#50
0"
#55
1"
#60
0"
#65
1"
#70
0"
#75
1"
#80
0"
#85
1"
#90
0"
#95
1"
#100
0"
#105
1"
#110
0"
#115
1"
#120
0"
#125
1"
#130
0"
#135
1"
#140
0"
#145
1"
#150
0"
#155
1"
#160
0"
#165
1"
#170
0"
#175
1"
#180
0"
#185
1"
#190
0"
#195
1"
#200
0"
1#
#205
b0 !
b0 $
1"
#210
0"
#215
1"
#220
0"
#225
1"
#230
0"
#235
1"
#240
0"
#245
1"
#250
0"
#255
1"
#260
0"
0#
#265
b1 !
b1 $
1"
#270
0"
#275
b10 !
b10 $
1"
#280
0"
#285
b11 !
b11 $
1"
#290
0"
#295
b100 !
b100 $
1"
#300
0"
#305
b101 !
b101 $
1"
#310
0"
#315
b110 !
b110 $
1"
#320
0"
#325
b111 !
b111 $
1"
#330
0"
#335
b1000 !
b1000 $
1"
#340
0"
#345
b1001 !
b1001 $
1"
#350
0"
#355
b1010 !
b1010 $
1"
#360
0"
#365
b1011 !
b1011 $
1"
#370
0"
#375
b1100 !
b1100 $
1"
#380
0"
#385
b1101 !
b1101 $
1"
#390
0"
#395
b1110 !
b1110 $
1"
#400
0"
#405
b1111 !
b1111 $
1"
#410
0"
#415
b10000 !
b10000 $
1"
#420
0"
#425
b10001 !
b10001 $
1"
#430
0"
#435
b10010 !
b10010 $
1"
#440
0"
#445
b10011 !
b10011 $
1"
#450
0"
#455
b10100 !
b10100 $
1"
#460
0"
#465
b10101 !
b10101 $
1"
#470
0"
#475
b10110 !
b10110 $
1"
#480
0"
#485
b10111 !
b10111 $
1"
#490
0"
#495
b11000 !
b11000 $
1"
#500
0"
#505
b11001 !
b11001 $
1"
#510
0"
#515
b11010 !
b11010 $
1"
#520
0"
#525
b11011 !
b11011 $
1"
#530
0"
#535
b11100 !
b11100 $
1"
#540
0"
#545
b11101 !
b11101 $
1"
#550
0"
#555
b11110 !
b11110 $
1"
#560
0"
#565
b11111 !
b11111 $
1"
#570
0"
#575
b100000 !
b100000 $
1"
#580
0"
#585
b100001 !
b100001 $
1"
#590
0"
#595
b100010 !
b100010 $
1"
#600
0"
#605
b100011 !
b100011 $
1"
#610
0"
#615
b100100 !
b100100 $
1"
#620
0"
#625
b100101 !
b100101 $
1"
#630
0"
#635
b100110 !
b100110 $
1"
#640
0"
#645
b100111 !
b100111 $
1"
#650
0"
#655
b101000 !
b101000 $
1"
#660
0"
#665
b101001 !
b101001 $
1"
#670
0"
#675
b101010 !
b101010 $
1"
#680
0"
#685
b101011 !
b101011 $
1"
#690
0"
#695
b101100 !
b101100 $
1"
#700
0"
#705
b101101 !
b101101 $
1"
#710
0"
#715
b101110 !
b101110 $
1"
#720
0"
#725
b101111 !
b101111 $
1"
#730
0"
#735
b110000 !
b110000 $
1"
#740
0"
#745
b110001 !
b110001 $
1"
#750
0"
#755
b110010 !
b110010 $
1"
#760
0"
#765
b110011 !
b110011 $
1"
#770
0"
#775
b110100 !
b110100 $
1"
#780
0"
#785
b110101 !
b110101 $
1"
#790
0"
#795
b110110 !
b110110 $
1"
#800
0"
#805
b110111 !
b110111 $
1"
#810
0"
#815
b111000 !
b111000 $
1"
#820
0"
#825
b111001 !
b111001 $
1"
#830
0"
#835
b111010 !
b111010 $
1"
#840
0"
#845
b111011 !
b111011 $
1"
#850
0"
#855
b111100 !
b111100 $
1"
#860
0"
#865
b111101 !
b111101 $
1"
#870
0"
#875
b111110 !
b111110 $
1"
#880
0"
#885
b111111 !
b111111 $
1"
#890
0"
#895
b1000000 !
b1000000 $
1"
#900
0"
#905
b1000001 !
b1000001 $
1"
#910
0"
#915
b1000010 !
b1000010 $
1"
#920
0"
#925
b1000011 !
b1000011 $
1"
#930
0"
#935
b1000100 !
b1000100 $
1"
#940
0"
#945
b1000101 !
b1000101 $
1"
#950
0"
#955
b1000110 !
b1000110 $
1"
#960
0"
#965
b1000111 !
b1000111 $
1"
#970
0"
#975
b1001000 !
b1001000 $
1"
#980
0"
#985
b1001001 !
b1001001 $
1"
#990
0"
#995
b1001010 !
b1001010 $
1"
#1000
0"
#1005
b1001011 !
b1001011 $
1"
#1010
0"
#1015
b1001100 !
b1001100 $
1"
#1020
0"
#1025
b1001101 !
b1001101 $
1"
#1030
0"
#1035
b1001110 !
b1001110 $
1"
#1040
0"
#1045
b1001111 !
b1001111 $
1"
#1050
0"
#1055
b1010000 !
b1010000 $
1"
#1060
0"
#1065
b1010001 !
b1010001 $
1"
#1070
0"
#1075
b1010010 !
b1010010 $
1"
#1080
0"
#1085
b1010011 !
b1010011 $
1"
#1090
0"
#1095
b1010100 !
b1010100 $
1"
#1100
0"
#1105
b1010101 !
b1010101 $
1"
#1110
0"
#1115
b1010110 !
b1010110 $
1"
#1120
0"
#1125
b1010111 !
b1010111 $
1"
#1130
0"
#1135
b1011000 !
b1011000 $
1"
#1140
0"
#1145
b1011001 !
b1011001 $
1"
#1150
0"
#1155
b1011010 !
b1011010 $
1"
#1160
0"
#1165
b1011011 !
b1011011 $
1"
#1170
0"
#1175
b1011100 !
b1011100 $
1"
#1180
0"
#1185
b1011101 !
b1011101 $
1"
#1190
0"
#1195
b1011110 !
b1011110 $
1"
#1200
0"
#1205
b1011111 !
b1011111 $
1"
#1210
0"
#1215
b1100000 !
b1100000 $
1"
#1220
0"
#1225
b1100001 !
b1100001 $
1"
#1230
0"
#1235
b1100010 !
b1100010 $
1"
#1240
0"
#1245
b1100011 !
b1100011 $
1"
#1250
0"
#1255
b1100100 !
b1100100 $
1"
#1260
0"
#1265
b1100101 !
b1100101 $
1"
#1270
0"
#1275
b1100110 !
b1100110 $
1"
#1280
0"
#1285
b1100111 !
b1100111 $
1"
#1290
0"
#1295
b1101000 !
b1101000 $
1"
#1300
0"
#1305
b1101001 !
b1101001 $
1"
#1310
0"
#1315
b1101010 !
b1101010 $
1"
#1320
0"
#1325
b1101011 !
b1101011 $
1"
#1330
0"
#1335
b1101100 !
b1101100 $
1"
#1340
0"
#1345
b1101101 !
b1101101 $
1"
#1350
0"
#1355
b1101110 !
b1101110 $
1"
#1360
0"
#1365
b1101111 !
b1101111 $
1"
#1370
0"
#1375
b1110000 !
b1110000 $
1"
#1380
0"
#1385
b1110001 !
b1110001 $
1"
#1390
0"
#1395
b1110010 !
b1110010 $
1"
#1400
0"
#1405
b1110011 !
b1110011 $
1"
#1410
0"
#1415
b1110100 !
b1110100 $
1"
#1420
0"
#1425
b1110101 !
b1110101 $
1"
#1430
0"
#1435
b1110110 !
b1110110 $
1"
#1440
0"
#1445
b1110111 !
b1110111 $
1"
#1450
0"
#1455
b1111000 !
b1111000 $
1"
