OneDrive/Desktop/75/week_6/src/mon/clk.v
module clk(
    input wire clk,
    input wire [7:0]data_in,
    input wire [3:0]addr,
    output wire[7:0] data_out,
    input wire wi_en

);
reg [7:0] mem[0:15];
always@(posedge clk) begin
    if (wi_en==1'b1)begin
        mem[addr] <=data_in;
    end
end
//here data will enter in exact same time when adder got value 
assign data_out=mem[addr];
endmodule

OneDrive/Desktop/75/week_6/src/mon/tb_clk.v
module tb_clk;
    reg clk;
    reg [7:0]data_in;
    reg wi_en;
    wire [7:0]data_out;
    reg [3:0]addr;
    clk uut(
        .data_in(data_in), .data_out(data_out), .wi_en(wi_en), .clk(clk), .addr(addr)
    );
    always #5 clk=~clk;
    initial begin
        $dumpfile("dump.vcd");
        $dumpvars(0,tb_clk);
        clk=0;
        data_in=7'd0;
        addr=4'd0;
        wi_en=1'b0;
        #10;
        wi_en=1'b1;addr=4'd4;data_in=8'hAA;#10;
        addr=4'd3;data_in=8'hBB;#10;
        addr=4'd2;data_in=8'hCC;#10;
        wi_en=1'b0;addr=4'd2;#10;
        addr=4'd3;#10;
        addr=4'd4;#10;
        $finish;
    end
endmodule

OneDrive/Desktop/75/week_6/src/mon/dump.vcd
$date
	Fri Jun 19 16:35:22 2026
$end
$version
	Icarus Verilog
$end
$timescale
	1s
$end
$scope module tb_clk $end
$var wire 8 ! data_out [7:0] $end
$var reg 4 " addr [3:0] $end
$var reg 1 # clk $end
$var reg 8 $ data_in [7:0] $end
$var reg 1 % wi_en $end
$scope module uut $end
$var wire 4 & addr [3:0] $end
$var wire 1 # clk $end
$var wire 8 ' data_in [7:0] $end
$var wire 8 ( data_out [7:0] $end
$var wire 1 % wi_en $end
$upscope $end
$upscope $end
$enddefinitions $end
#0
$dumpvars
bx (
b0 '
b0 &
0%
b0 $
0#
b0 "
bx !
$end
#5
1#
#10
0#
b10101010 $
b10101010 '
b100 "
b100 &
1%
#15
b10101010 !
b10101010 (
1#
#20
0#
b10111011 $
b10111011 '
bx !
bx (
b11 "
b11 &
#25
b10111011 !
b10111011 (
1#
#30
0#
b11001100 $
b11001100 '
bx !
bx (
b10 "
b10 &
#35
b11001100 !
b11001100 (
1#
#40
0#
0%
#45
1#
#50
0#
b10111011 !
b10111011 (
b11 "
b11 &
#55
1#
#60
0#
b10101010 !
b10101010 (
b100 "
b100 &
