OneDrive/Desktop/75/week_2/full_adder/or_gate.v

module or_gate(
    input a,
    input b,
    output y
);

    assign y = a||b;
endmodule

OneDrive/Desktop/75/week_2/full_adder/half_adder.v
module half_adder(
    input wire a,
    input wire b,
    output wire carry,
    output wire sum
);
    assign sum=a^b;
    assign carry =a&b;
endmodule

OneDrive/Desktop/75/week_2/n_bitadder/full_adder.v
module full_adder(
    input wire a,
    input wire b,
    input wire cin,
    output wire sum,
    output wire cout
);

    // Internal wires to connect the chips together
    wire sum1;
    wire carry1;
    wire carry2;

    // Instantiate First Half Adder
    half_adder HA1 (
        .a(a), 
        .b(b), 
        .sum(sum1), 
        .carry(carry1)
    );

    // Instantiate Second Half Adder
    half_adder HA2 (
        .a(sum1), 
        .b(cin), 
        .sum(sum), 
        .carry(carry2)
    );

    // Instantiate OR Gate for the final carry
    or_gate OR1 (
        .a(carry1), 
        .b(carry2), 
        .y(cout)
    );

endmodule

OneDrive/Desktop/75/week_2/full_adder/ripple_carry_4bit.v
module ripple_carry_4bit(
    input wire [3:0] A,
    input wire [3:0] B,
    input wire cin,
    output wire [3:0] sum,
    output wire cout
);

    wire carry1, carry2, carry3;
    full_adder FA0 (.a(A[0]), .b(B[0]), .cin(cin),    .sum(sum[0]), .cout(carry1));
    full_adder FA1 (.a(A[1]), .b(B[1]), .cin(carry1), .sum(sum[1]), .cout(carry2));
    full_adder FA2 (.a(A[2]), .b(B[2]), .cin(carry2), .sum(sum[2]), .cout(carry3));
    full_adder FA3 (.a(A[3]), .b(B[3]), .cin(carry3), .sum(sum[3]), .cout(cout));

endmodule

OneDrive/Desktop/75/week_2/full_adder/tb_4bit_adder.v

module tb_4bit_adder;

    reg [3:0] A;
    reg [3:0] B;
    reg cin;
    
    wire [3:0] sum;
    wire cout;

    // Instantiate the 4-bit adder system
    ripple_carry_4bit uut (
        .A(A), 
        .B(B), 
        .cin(cin), 
        .sum(sum), 
        .cout(cout)
    );

    integer i, j;

    initial begin
        $dumpfile("dump.vcd");
        $dumpvars(0, tb_4bit_adder);

        cin = 0; // Lock cin to 0 for this test

        // Your exact nested loop logic - this is perfect!
        for(i = 0; i < 16; i = i + 1) begin
            A = i;
            for(j = 0; j < 16; j = j + 1) begin
                B = j; 
                #10;
            end
        end

        $finish;
    end

endmodule

OneDrive/Desktop/75/week_2/full_adder/dump.vcd
$date
	Fri May 29 22:11:18 2026
$end
$version
	Icarus Verilog
$end
$timescale
	1s
$end
$scope module tb_4bit_adder $end
$var wire 4 ! sum [3:0] $end
$var wire 1 " cout $end
$var reg 4 # A [3:0] $end
$var reg 4 $ B [3:0] $end
$var reg 1 % cin $end
$var integer 32 & i [31:0] $end
$var integer 32 ' j [31:0] $end
$scope module uut $end
$var wire 4 ( A [3:0] $end
$var wire 4 ) B [3:0] $end
$var wire 1 % cin $end
$var wire 4 * sum [3:0] $end
$var wire 1 " cout $end
$var wire 1 + carry3 $end
$var wire 1 , carry2 $end
$var wire 1 - carry1 $end
$scope module FA0 $end
$var wire 1 . a $end
$var wire 1 / b $end
$var wire 1 % cin $end
$var wire 1 0 sum1 $end
$var wire 1 1 sum $end
$var wire 1 + cout $end
$var wire 1 2 carry2 $end
$var wire 1 3 carry1 $end
$scope module HA1 $end
$var wire 1 . a $end
$var wire 1 / b $end
$var wire 1 3 carry $end
$var wire 1 0 sum $end
$upscope $end
$scope module HA2 $end
$var wire 1 0 a $end
$var wire 1 % b $end
$var wire 1 2 carry $end
$var wire 1 1 sum $end
$upscope $end
$scope module OR1 $end
$var wire 1 3 a $end
$var wire 1 2 b $end
$var wire 1 + y $end
$upscope $end
$upscope $end
$scope module FA1 $end
$var wire 1 4 a $end
$var wire 1 5 b $end
$var wire 1 + cin $end
$var wire 1 6 sum1 $end
$var wire 1 7 sum $end
$var wire 1 - cout $end
$var wire 1 8 carry2 $end
$var wire 1 9 carry1 $end
$scope module HA1 $end
$var wire 1 4 a $end
$var wire 1 5 b $end
$var wire 1 9 carry $end
$var wire 1 6 sum $end
$upscope $end
$scope module HA2 $end
$var wire 1 6 a $end
$var wire 1 + b $end
$var wire 1 8 carry $end
$var wire 1 7 sum $end
$upscope $end
$scope module OR1 $end
$var wire 1 9 a $end
$var wire 1 8 b $end
$var wire 1 - y $end
$upscope $end
$upscope $end
$scope module FA2 $end
$var wire 1 : a $end
$var wire 1 ; b $end
$var wire 1 < sum1 $end
$var wire 1 = sum $end
$var wire 1 , cout $end
$var wire 1 , cin $end
$var wire 1 > carry2 $end
$var wire 1 ? carry1 $end
$scope module HA1 $end
$var wire 1 : a $end
$var wire 1 ; b $end
$var wire 1 ? carry $end
$var wire 1 < sum $end
$upscope $end
$scope module HA2 $end
$var wire 1 < a $end
$var wire 1 > carry $end
$var wire 1 = sum $end
$var wire 1 , b $end
$upscope $end
$scope module OR1 $end
$var wire 1 ? a $end
$var wire 1 > b $end
$var wire 1 , y $end
$upscope $end
$upscope $end
$scope module FA3 $end
$var wire 1 @ a $end
$var wire 1 A b $end
$var wire 1 - cin $end
$var wire 1 B sum1 $end
$var wire 1 C sum $end
$var wire 1 " cout $end
$var wire 1 D carry2 $end
$var wire 1 E carry1 $end
$scope module HA1 $end
$var wire 1 @ a $end
$var wire 1 A b $end
$var wire 1 E carry $end
$var wire 1 B sum $end
$upscope $end
$scope module HA2 $end
$var wire 1 B a $end
$var wire 1 - b $end
$var wire 1 D carry $end
$var wire 1 C sum $end
$upscope $end
$scope module OR1 $end
$var wire 1 E a $end
$var wire 1 D b $end
$var wire 1 " y $end
$upscope $end
$upscope $end
$upscope $end
$upscope $end
$enddefinitions $end
#0
$dumpvars
0E
0D
0C
0B
0A
0@
0?
0>
0=
0<
0;
0:
09
08
07
06
05
04
03
02
01
00
0/
0.
0-
0,
0+
b0 *
b0 )
b0 (
b0 '
b0 &
0%
b0 $
b0 #
0"
b0 !
$end
#10
b1 !
b1 *
11
10
1/
b1 $
b1 )
b1 '
#20
01
b10 !
b10 *
17
00
16
0/
15
b10 $
b10 )
b10 '
#30
b11 !
b11 *
11
10
1/
b11 $
b11 )
b11 '
#40
01
07
b100 !
b100 *
1=
00
06
1<
0/
05
1;
b100 $
b100 )
b100 '
#50
b101 !
b101 *
11
10
1/
b101 $
b101 )
b101 '
#60
01
b110 !
b110 *
17
00
16
0/
15
b110 $
b110 )
b110 '
#70
b111 !
b111 *
11
10
1/
b111 $
b111 )
b111 '
#80
01
07
0=
b1000 !
b1000 *
1C
00
06
0<
1B
0/
05
0;
1A
b1000 $
b1000 )
b1000 '
#90
b1001 !
b1001 *
11
10
1/
b1001 $
b1001 )
b1001 '
#100
01
b1010 !
b1010 *
17
00
16
0/
15
b1010 $
b1010 )
b1010 '
#110
b1011 !
b1011 *
11
10
1/
b1011 $
b1011 )
b1011 '
#120
01
07
b1100 !
b1100 *
1=
00
06
1<
0/
05
1;
b1100 $
b1100 )
b1100 '
#130
b1101 !
b1101 *
11
10
1/
b1101 $
b1101 )
b1101 '
#140
01
b1110 !
b1110 *
17
00
16
0/
15
b1110 $
b1110 )
b1110 '
#150
b1111 !
b1111 *
11
10
1/
b1111 $
b1111 )
b1111 '
#160
07
0=
b1 !
b1 *
0C
06
0<
0B
0/
05
0;
0A
1.
b0 $
b0 )
b1 #
b1 (
b1 &
b0 '
#170
17
b10 !
b10 *
01
1+
00
13
1/
b1 $
b1 )
b1 '
#180
0C
0-
11
0+
b11 !
b11 *
17
08
10
03
16
0/
15
b10 $
b10 )
b10 '
#190
1C
1-
07
18
b1000 !
b1000 *
01
1+
00
13
1/
b11 $
b11 )
b11 '
#200
0C
0-
11
0+
07
08
b101 !
b101 *
1=
10
03
06
1<
0/
05
1;
b100 $
b100 )
b100 '
#210
17
b110 !
b110 *
01
1+
00
13
1/
b101 $
b101 )
b101 '
#220
0C
0-
11
0+
b111 !
b111 *
17
08
10
03
16
0/
15
b110 $
b110 )
b110 '
#230
1C
1-
07
18
b1100 !
b1100 *
01
1+
00
13
1/
b111 $
b111 )
b111 '
#240
0-
0"
11
0+
07
08
0=
b1001 !
b1001 *
1C
0D
10
03
06
0<
1B
0/
05
0;
1A
b1000 $
b1000 )
b1000 '
#250
17
b1010 !
b1010 *
01
1+
00
13
1/
b1001 $
b1001 )
b1001 '
#260
0"
1C
0D
0-
11
0+
b1011 !
b1011 *
17
08
10
03
16
0/
15
b1010 $
b1010 )
b1010 '
#270
1"
0C
1D
1-
07
18
b0 !
b0 *
01
1+
00
13
1/
b1011 $
b1011 )
b1011 '
#280
0"
1C
0D
0-
11
0+
07
08
b1101 !
b1101 *
1=
10
03
06
1<
0/
05
1;
b1100 $
b1100 )
b1100 '
#290
17
b1110 !
b1110 *
01
1+
00
13
1/
b1101 $
b1101 )
b1101 '
#300
0"
1C
0D
0-
11
0+
b1111 !
b1111 *
17
08
10
03
16
0/
15
b1110 $
b1110 )
b1110 '
#310
1"
0C
1D
1-
07
18
b100 !
b100 *
01
1+
00
13
1/
b1111 $
b1111 )
b1111 '
#320
0-
0"
17
08
0=
b10 !
b10 *
0C
0D
0+
0<
0B
03
0/
05
0;
0A
0.
14
b0 $
b0 )
b10 #
b10 (
b10 &
b0 '
#330
b11 !
b11 *
11
10
1/
b1 $
b1 )
b1 '
#340
1C
01
b1000 !
b1000 *
07
1-
00
06
19
0/
15
b10 $
b10 )
b10 '
#350
b1001 !
b1001 *
11
10
1/
b11 $
b11 )
b11 '
#360
0C
01
17
0-
b110 !
b110 *
1=
00
16
09
1<
0/
05
1;
b100 $
b100 )
b100 '
#370
b111 !
b111 *
11
10
1/
b101 $
b101 )
b101 '
#380
1C
01
b1100 !
b1100 *
07
1-
00
06
19
0/
15
b110 $
b110 )
b110 '
#390
b1101 !
b1101 *
11
10
1/
b111 $
b111 )
b111 '
#400
0"
01
17
0-
0=
b1010 !
b1010 *
1C
0D
00
16
09
0<
1B
0/
05
0;
1A
b1000 $
b1000 )
b1000 '
#410
b1011 !
b1011 *
11
10
1/
b1001 $
b1001 )
b1001 '
#420
1"
0C
1D
01
b0 !
b0 *
07
1-
00
06
19
0/
15
b1010 $
b1010 )
b1010 '
#430
b1 !
b1 *
11
10
1/
b1011 $
b1011 )
b1011 '
#440
0"
1C
0D
01
17
0-
b1110 !
b1110 *
1=
00
16
09
1<
0/
05
1;
b1100 $
b1100 )
b1100 '
#450
b1111 !
b1111 *
11
10
1/
b1101 $
b1101 )
b1101 '
#460
1"
0C
1D
01
b100 !
b100 *
07
1-
00
06
19
0/
15
b1110 $
b1110 )
b1110 '
#470
b101 !
b101 *
11
10
1/
b1111 $
b1111 )
b1111 '
#480
0"
17
0-
0=
b11 !
b11 *
0C
0D
16
09
0<
0B
0/
05
0;
0A
1.
b0 $
b0 )
b11 #
b11 (
b11 &
b0 '
#490
1C
1-
07
18
b1000 !
b1000 *
01
1+
00
13
1/
b1 $
b1 )
b1 '
#500
11
0+
b1001 !
b1001 *
07
08
10
03
06
19
0/
15
b10 $
b10 )
b10 '
#510
17
b1010 !
b1010 *
01
1+
00
13
1/
b11 $
b11 )
b11 '
#520
0C
11
0+
17
08
0-
b111 !
b111 *
1=
10
03
16
09
1<
0/
05
1;
b100 $
b100 )
b100 '
#530
1C
1-
07
18
b1100 !
b1100 *
01
1+
00
13
1/
b101 $
b101 )
b101 '
#540
11
0+
b1101 !
b1101 *
07
08
10
03
06
19
0/
15
b110 $
b110 )
b110 '
#550
17
b1110 !
b1110 *
01
1+
00
13
1/
b111 $
b111 )
b111 '
#560
0"
11
0+
17
08
0-
0=
b1011 !
b1011 *
1C
0D
10
03
16
09
0<
1B
0/
05
0;
1A
b1000 $
b1000 )
b1000 '
#570
1"
0C
1D
1-
07
18
b0 !
b0 *
01
1+
00
13
1/
b1001 $
b1001 )
b1001 '
#580
11
0+
b1 !
b1 *
07
08
10
03
06
19
0/
15
b1010 $
b1010 )
b1010 '
#590
17
b10 !
b10 *
01
1+
00
13
1/
b1011 $
b1011 )
b1011 '
#600
0"
1C
0D
11
0+
17
08
0-
b1111 !
b1111 *
1=
10
03
16
09
1<
0/
05
1;
b1100 $
b1100 )
b1100 '
#610
1"
0C
1D
1-
07
18
b100 !
b100 *
01
1+
00
13
1/
b1101 $
b1101 )
b1101 '
#620
11
0+
b101 !
b101 *
07
08
10
03
06
19
0/
15
b1110 $
b1110 )
b1110 '
#630
17
b110 !
b110 *
01
1+
00
13
1/
b1111 $
b1111 )
b1111 '
#640
0"
b100 !
b100 *
07
0D
0+
0-
0B
03
09
0/
05
0;
0A
0.
04
1:
b0 $
b0 )
b100 #
b100 (
b100 &
b0 '
#650
b101 !
b101 *
11
10
1/
b1 $
b1 )
b1 '
#660
01
b110 !
b110 *
17
00
16
0/
15
b10 $
b10 )
b10 '
#670
b111 !
b111 *
11
10
1/
b11 $
b11 )
b11 '
#680
01
b100 !
b100 *
07
1,
00
06
0<
1?
0/
05
1;
b100 $
b100 )
b100 '
#690
b101 !
b101 *
11
10
1/
b101 $
b101 )
b101 '
#700
01
b110 !
b110 *
17
00
16
0/
15
b110 $
b110 )
b110 '
#710
b111 !
b111 *
11
10
1/
b111 $
b111 )
b111 '
#720
01
07
0,
b1100 !
b1100 *
1C
00
06
1<
0?
1B
0/
05
0;
1A
b1000 $
b1000 )
b1000 '
#730
b1101 !
b1101 *
11
10
1/
b1001 $
b1001 )
b1001 '
#740
01
b1110 !
b1110 *
17
00
16
0/
15
b1010 $
b1010 )
b1010 '
#750
b1111 !
b1111 *
11
10
1/
b1011 $
b1011 )
b1011 '
#760
01
b1100 !
b1100 *
07
1,
00
06
0<
1?
0/
05
1;
b1100 $
b1100 )
b1100 '
#770
b1101 !
b1101 *
11
10
1/
b1101 $
b1101 )
b1101 '
#780
01
b1110 !
b1110 *
17
00
16
0/
15
b1110 $
b1110 )
b1110 '
#790
b1111 !
b1111 *
11
10
1/
b1111 $
b1111 )
b1111 '
#800
07
0,
b101 !
b101 *
0C
06
1<
0?
0B
0/
05
0;
0A
1.
b0 $
b0 )
b101 #
b101 (
b101 &
b0 '
#810
17
b110 !
b110 *
01
1+
00
13
1/
b1 $
b1 )
b1 '
#820
0C
0-
11
0+
b111 !
b111 *
17
08
10
03
16
0/
15
b10 $
b10 )
b10 '
#830
1C
1-
07
18
b1100 !
b1100 *
01
1+
00
13
1/
b11 $
b11 )
b11 '
#840
0C
0-
11
0+
b101 !
b101 *
07
08
1,
10
03
06
0<
1?
0/
05
1;
b100 $
b100 )
b100 '
#850
17
b110 !
b110 *
01
1+
00
13
1/
b101 $
b101 )
b101 '
#860
0C
0-
11
0+
b111 !
b111 *
17
08
10
03
16
0/
15
b110 $
b110 )
b110 '
#870
1C
1-
07
18
b1100 !
b1100 *
01
1+
00
13
1/
b111 $
b111 )
b111 '
#880
0-
0"
11
0+
07
08
0,
b1101 !
b1101 *
1C
0D
10
03
06
1<
0?
1B
0/
05
0;
1A
b1000 $
b1000 )
b1000 '
#890
17
b1110 !
b1110 *
01
1+
00
13
1/
b1001 $
b1001 )
b1001 '
#900
0"
1C
0D
0-
11
0+
b1111 !
b1111 *
17
08
10
03
16
0/
15
b1010 $
b1010 )
b1010 '
#910
1"
0C
1D
1-
07
18
b100 !
b100 *
01
1+
00
13
1/
b1011 $
b1011 )
b1011 '
#920
0"
1C
0D
0-
11
0+
b1101 !
b1101 *
07
08
1,
10
03
06
0<
1?
0/
05
1;
b1100 $
b1100 )
b1100 '
#930
17
b1110 !
b1110 *
01
1+
00
13
1/
b1101 $
b1101 )
b1101 '
#940
0"
1C
0D
0-
11
0+
b1111 !
b1111 *
17
08
10
03
16
0/
15
b1110 $
b1110 )
b1110 '
#950
1"
0C
1D
1-
07
18
b100 !
b100 *
01
1+
00
13
1/
b1111 $
b1111 )
b1111 '
#960
0-
0"
17
08
0,
b110 !
b110 *
0C
0D
0+
1<
0?
0B
03
0/
05
0;
0A
0.
14
b0 $
b0 )
b110 #
b110 (
b110 &
b0 '
#970
b111 !
b111 *
11
10
1/
b1 $
b1 )
b1 '
#980
1C
01
b1100 !
b1100 *
07
1-
00
06
19
0/
15
b10 $
b10 )
b10 '
#990
b1101 !
b1101 *
11
10
1/
b11 $
b11 )
b11 '
#1000
0C
01
b110 !
b110 *
17
0-
1,
00
16
09
0<
1?
0/
05
1;
b100 $
b100 )
b100 '
#1010
b111 !
b111 *
11
10
1/
b101 $
b101 )
b101 '
#1020
1C
01
b1100 !
b1100 *
07
1-
00
06
19
0/
15
b110 $
b110 )
b110 '
#1030
b1101 !
b1101 *
11
10
1/
b111 $
b111 )
b111 '
#1040
0"
01
17
0-
0,
b1110 !
b1110 *
1C
0D
00
16
09
1<
0?
1B
0/
05
0;
1A
b1000 $
b1000 )
b1000 '
#1050
b1111 !
b1111 *
11
10
1/
b1001 $
b1001 )
b1001 '
#1060
1"
0C
1D
01
b100 !
b100 *
07
1-
00
06
19
0/
15
b1010 $
b1010 )
b1010 '
#1070
b101 !
b101 *
11
10
1/
b1011 $
b1011 )
b1011 '
#1080
0"
1C
0D
01
b1110 !
b1110 *
17
0-
1,
00
16
09
0<
1?
0/
05
1;
b1100 $
b1100 )
b1100 '
#1090
b1111 !
b1111 *
11
10
1/
b1101 $
b1101 )
b1101 '
#1100
1"
0C
1D
01
b100 !
b100 *
07
1-
00
06
19
0/
15
b1110 $
b1110 )
b1110 '
#1110
b101 !
b101 *
11
10
1/
b1111 $
b1111 )
b1111 '
#1120
0"
17
0-
0,
b111 !
b111 *
0C
0D
16
09
1<
0?
0B
0/
05
0;
0A
1.
b0 $
b0 )
b111 #
b111 (
b111 &
b0 '
#1130
1C
1-
07
18
b1100 !
b1100 *
01
1+
00
13
1/
b1 $
b1 )
b1 '
#1140
11
0+
b1101 !
b1101 *
07
08
10
03
06
19
0/
15
b10 $
b10 )
b10 '
#1150
17
b1110 !
b1110 *
01
1+
00
13
1/
b11 $
b11 )
b11 '
#1160
0C
11
0+
b111 !
b111 *
17
08
0-
1,
10
03
16
09
0<
1?
0/
05
1;
b100 $
b100 )
b100 '
#1170
1C
1-
07
18
b1100 !
b1100 *
01
1+
00
13
1/
b101 $
b101 )
b101 '
#1180
11
0+
b1101 !
b1101 *
07
08
10
03
06
19
0/
15
b110 $
b110 )
b110 '
#1190
17
b1110 !
b1110 *
01
1+
00
13
1/
b111 $
b111 )
b111 '
#1200
0"
11
0+
17
08
0-
0,
b1111 !
b1111 *
1C
0D
10
03
16
09
1<
0?
1B
0/
05
0;
1A
b1000 $
b1000 )
b1000 '
#1210
1"
0C
1D
1-
07
18
b100 !
b100 *
01
1+
00
13
1/
b1001 $
b1001 )
b1001 '
#1220
11
0+
b101 !
b101 *
07
08
10
03
06
19
0/
15
b1010 $
b1010 )
b1010 '
#1230
17
b110 !
b110 *
01
1+
00
13
1/
b1011 $
b1011 )
b1011 '
#1240
0"
1C
0D
11
0+
b1111 !
b1111 *
17
08
0-
1,
10
03
16
09
0<
1?
0/
05
1;
b1100 $
b1100 )
b1100 '
#1250
1"
0C
1D
1-
07
18
b100 !
b100 *
01
1+
00
13
1/
b1101 $
b1101 )
b1101 '
#1260
11
0+
b101 !
b101 *
07
08
10
03
06
19
0/
15
b1110 $
b1110 )
b1110 '
#1270
17
b110 !
b110 *
01
1+
00
13
1/
b1111 $
b1111 )
b1111 '
#1280
0"
07
1C
0D
b1000 !
b1000 *
0=
0+
0-
0,
03
09
0?
0/
05
0;
0A
0.
04
0:
1@
b0 $
b0 )
b1000 #
b1000 (
b1000 &
b0 '
#1290
b1001 !
b1001 *
11
10
1/
b1 $
b1 )
b1 '
#1300
01
b1010 !
b1010 *
17
00
16
0/
15
b10 $
b10 )
b10 '
#1310
b1011 !
b1011 *
11
10
1/
b11 $
b11 )
b11 '
#1320
01
07
b1100 !
b1100 *
1=
00
06
1<
0/
05
1;
b100 $
b100 )
b100 '
#1330
b1101 !
b1101 *
11
10
1/
b101 $
b101 )
b101 '
#1340
01
b1110 !
b1110 *
17
00
16
0/
15
b110 $
b110 )
b110 '
#1350
b1111 !
b1111 *
11
10
1/
b111 $
b111 )
b111 '
#1360
01
07
0=
b0 !
b0 *
0C
1"
00
06
0<
0B
1E
0/
05
0;
1A
b1000 $
b1000 )
b1000 '
#1370
b1 !
b1 *
11
10
1/
b1001 $
b1001 )
b1001 '
#1380
01
b10 !
b10 *
17
00
16
0/
15
b1010 $
b1010 )
b1010 '
#1390
b11 !
b11 *
11
10
1/
b1011 $
b1011 )
b1011 '
#1400
01
07
b100 !
b100 *
1=
00
06
1<
0/
05
1;
b1100 $
b1100 )
b1100 '
#1410
b101 !
b101 *
11
10
1/
b1101 $
b1101 )
b1101 '
#1420
01
b110 !
b110 *
17
00
16
0/
15
b1110 $
b1110 )
b1110 '
#1430
b111 !
b111 *
11
10
1/
b1111 $
b1111 )
b1111 '
#1440
07
0=
b1001 !
b1001 *
1C
0"
06
0<
1B
0E
0/
05
0;
0A
1.
b0 $
b0 )
b1001 #
b1001 (
b1001 &
b0 '
#1450
17
b1010 !
b1010 *
01
1+
00
13
1/
b1 $
b1 )
b1 '
#1460
0"
1C
0D
0-
11
0+
b1011 !
b1011 *
17
08
10
03
16
0/
15
b10 $
b10 )
b10 '
#1470
1"
0C
1D
1-
07
18
b0 !
b0 *
01
1+
00
13
1/
b11 $
b11 )
b11 '
#1480
0"
1C
0D
0-
11
0+
07
08
b1101 !
b1101 *
1=
10
03
06
1<
0/
05
1;
b100 $
b100 )
b100 '
#1490
17
b1110 !
b1110 *
01
1+
00
13
1/
b101 $
b101 )
b101 '
#1500
0"
1C
0D
0-
11
0+
b1111 !
b1111 *
17
08
10
03
16
0/
15
b110 $
b110 )
b110 '
#1510
1"
0C
1D
1-
07
18
b100 !
b100 *
01
1+
00
13
1/
b111 $
b111 )
b111 '
#1520
0-
11
0+
07
08
0=
b1 !
b1 *
0C
0D
10
03
06
0<
0B
1E
0/
05
0;
1A
b1000 $
b1000 )
b1000 '
#1530
17
b10 !
b10 *
01
1+
00
13
1/
b1001 $
b1001 )
b1001 '
#1540
0C
0-
11
0+
b11 !
b11 *
17
08
10
03
16
0/
15
b1010 $
b1010 )
b1010 '
#1550
1C
1-
07
18
b1000 !
b1000 *
01
1+
00
13
1/
b1011 $
b1011 )
b1011 '
#1560
0C
0-
11
0+
07
08
b101 !
b101 *
1=
10
03
06
1<
0/
05
1;
b1100 $
b1100 )
b1100 '
#1570
17
b110 !
b110 *
01
1+
00
13
1/
b1101 $
b1101 )
b1101 '
#1580
0C
0-
11
0+
b111 !
b111 *
17
08
10
03
16
0/
15
b1110 $
b1110 )
b1110 '
#1590
1C
1-
07
18
b1100 !
b1100 *
01
1+
00
13
1/
b1111 $
b1111 )
b1111 '
#1600
0-
17
08
0=
b1010 !
b1010 *
1C
0D
0"
0+
0<
1B
0E
03
0/
05
0;
0A
0.
14
b0 $
b0 )
b1010 #
b1010 (
b1010 &
b0 '
#1610
b1011 !
b1011 *
11
10
1/
b1 $
b1 )
b1 '
#1620
1"
0C
1D
01
b0 !
b0 *
07
1-
00
06
19
0/
15
b10 $
b10 )
b10 '
#1630
b1 !
b1 *
11
10
1/
b11 $
b11 )
b11 '
#1640
0"
1C
0D
01
17
0-
b1110 !
b1110 *
1=
00
16
09
1<
0/
05
1;
b100 $
b100 )
b100 '
#1650
b1111 !
b1111 *
11
10
1/
b101 $
b101 )
b101 '
#1660
1"
0C
1D
01
b100 !
b100 *
07
1-
00
06
19
0/
15
b110 $
b110 )
b110 '
#1670
b101 !
b101 *
11
10
1/
b111 $
b111 )
b111 '
#1680
01
17
0-
0=
b10 !
b10 *
0C
0D
00
16
09
0<
0B
1E
0/
05
0;
1A
b1000 $
b1000 )
b1000 '
#1690
b11 !
b11 *
11
10
1/
b1001 $
b1001 )
b1001 '
#1700
1C
01
b1000 !
b1000 *
07
1-
00
06
19
0/
15
b1010 $
b1010 )
b1010 '
#1710
b1001 !
b1001 *
11
10
1/
b1011 $
b1011 )
b1011 '
#1720
0C
01
17
0-
b110 !
b110 *
1=
00
16
09
1<
0/
05
1;
b1100 $
b1100 )
b1100 '
#1730
b111 !
b111 *
11
10
1/
b1101 $
b1101 )
b1101 '
#1740
1C
01
b1100 !
b1100 *
07
1-
00
06
19
0/
15
b1110 $
b1110 )
b1110 '
#1750
b1101 !
b1101 *
11
10
1/
b1111 $
b1111 )
b1111 '
#1760
17
0-
0=
b1011 !
b1011 *
1C
0D
0"
16
09
0<
1B
0E
0/
05
0;
0A
1.
b0 $
b0 )
b1011 #
b1011 (
b1011 &
b0 '
#1770
1"
0C
1D
1-
07
18
b0 !
b0 *
01
1+
00
13
1/
b1 $
b1 )
b1 '
#1780
11
0+
b1 !
b1 *
07
08
10
03
06
19
0/
15
b10 $
b10 )
b10 '
#1790
17
b10 !
b10 *
01
1+
00
13
1/
b11 $
b11 )
b11 '
#1800
0"
1C
0D
11
0+
17
08
0-
b1111 !
b1111 *
1=
10
03
16
09
1<
0/
05
1;
b100 $
b100 )
b100 '
#1810
1"
0C
1D
1-
07
18
b100 !
b100 *
01
1+
00
13
1/
b101 $
b101 )
b101 '
#1820
11
0+
b101 !
b101 *
07
08
10
03
06
19
0/
15
b110 $
b110 )
b110 '
#1830
17
b110 !
b110 *
01
1+
00
13
1/
b111 $
b111 )
b111 '
#1840
11
0+
17
08
0-
0=
b11 !
b11 *
0C
0D
10
03
16
09
0<
0B
1E
0/
05
0;
1A
b1000 $
b1000 )
b1000 '
#1850
1C
1-
07
18
b1000 !
b1000 *
01
1+
00
13
1/
b1001 $
b1001 )
b1001 '
#1860
11
0+
b1001 !
b1001 *
07
08
10
03
06
19
0/
15
b1010 $
b1010 )
b1010 '
#1870
17
b1010 !
b1010 *
01
1+
00
13
1/
b1011 $
b1011 )
b1011 '
#1880
0C
11
0+
17
08
0-
b111 !
b111 *
1=
10
03
16
09
1<
0/
05
1;
b1100 $
b1100 )
b1100 '
#1890
1C
1-
07
18
b1100 !
b1100 *
01
1+
00
13
1/
b1101 $
b1101 )
b1101 '
#1900
11
0+
b1101 !
b1101 *
07
08
10
03
06
19
0/
15
b1110 $
b1110 )
b1110 '
#1910
17
b1110 !
b1110 *
01
1+
00
13
1/
b1111 $
b1111 )
b1111 '
#1920
b1100 !
b1100 *
07
0"
0+
0-
1B
0E
03
09
0/
05
0;
0A
0.
04
1:
b0 $
b0 )
b1100 #
b1100 (
b1100 &
b0 '
#1930
b1101 !
b1101 *
11
10
1/
b1 $
b1 )
b1 '
#1940
01
b1110 !
b1110 *
17
00
16
0/
15
b10 $
b10 )
b10 '
#1950
b1111 !
b1111 *
11
10
1/
b11 $
b11 )
b11 '
#1960
01
b1100 !
b1100 *
07
1,
00
06
0<
1?
0/
05
1;
b100 $
b100 )
b100 '
#1970
b1101 !
b1101 *
11
10
1/
b101 $
b101 )
b101 '
#1980
01
b1110 !
b1110 *
17
00
16
0/
15
b110 $
b110 )
b110 '
#1990
b1111 !
b1111 *
11
10
1/
b111 $
b111 )
b111 '
#2000
01
07
0,
b100 !
b100 *
0C
1"
00
06
1<
0?
0B
1E
0/
05
0;
1A
b1000 $
b1000 )
b1000 '
#2010
b101 !
b101 *
11
10
1/
b1001 $
b1001 )
b1001 '
#2020
01
b110 !
b110 *
17
00
16
0/
15
b1010 $
b1010 )
b1010 '
#2030
b111 !
b111 *
11
10
1/
b1011 $
b1011 )
b1011 '
#2040
01
b100 !
b100 *
07
1,
00
06
0<
1?
0/
05
1;
b1100 $
b1100 )
b1100 '
#2050
b101 !
b101 *
11
10
1/
b1101 $
b1101 )
b1101 '
#2060
01
b110 !
b110 *
17
00
16
0/
15
b1110 $
b1110 )
b1110 '
#2070
b111 !
b111 *
11
10
1/
b1111 $
b1111 )
b1111 '
#2080
07
0,
b1101 !
b1101 *
1C
0"
06
1<
0?
1B
0E
0/
05
0;
0A
1.
b0 $
b0 )
b1101 #
b1101 (
b1101 &
b0 '
#2090
17
b1110 !
b1110 *
01
1+
00
13
1/
b1 $
b1 )
b1 '
#2100
0"
1C
0D
0-
11
0+
b1111 !
b1111 *
17
08
10
03
16
0/
15
b10 $
b10 )
b10 '
#2110
1"
0C
1D
1-
07
18
b100 !
b100 *
01
1+
00
13
1/
b11 $
b11 )
b11 '
#2120
0"
1C
0D
0-
11
0+
b1101 !
b1101 *
07
08
1,
10
03
06
0<
1?
0/
05
1;
b100 $
b100 )
b100 '
#2130
17
b1110 !
b1110 *
01
1+
00
13
1/
b101 $
b101 )
b101 '
#2140
0"
1C
0D
0-
11
0+
b1111 !
b1111 *
17
08
10
03
16
0/
15
b110 $
b110 )
b110 '
#2150
1"
0C
1D
1-
07
18
b100 !
b100 *
01
1+
00
13
1/
b111 $
b111 )
b111 '
#2160
0-
11
0+
07
08
0,
b101 !
b101 *
0C
0D
10
03
06
1<
0?
0B
1E
0/
05
0;
1A
b1000 $
b1000 )
b1000 '
#2170
17
b110 !
b110 *
01
1+
00
13
1/
b1001 $
b1001 )
b1001 '
#2180
0C
0-
11
0+
b111 !
b111 *
17
08
10
03
16
0/
15
b1010 $
b1010 )
b1010 '
#2190
1C
1-
07
18
b1100 !
b1100 *
01
1+
00
13
1/
b1011 $
b1011 )
b1011 '
#2200
0C
0-
11
0+
b101 !
b101 *
07
08
1,
10
03
06
0<
1?
0/
05
1;
b1100 $
b1100 )
b1100 '
#2210
17
b110 !
b110 *
01
1+
00
13
1/
b1101 $
b1101 )
b1101 '
#2220
0C
0-
11
0+
b111 !
b111 *
17
08
10
03
16
0/
15
b1110 $
b1110 )
b1110 '
#2230
1C
1-
07
18
b1100 !
b1100 *
01
1+
00
13
1/
b1111 $
b1111 )
b1111 '
