OneDrive/Desktop/75/week_4/src/mon_code/counter_4bit.v
module counter_4bit(
    input wire rst,
    input wire clk,
    input wire enable,
    input wire updown,
    output reg [3:0]q

);
always @(posedge clk) begin
    if(rst==1) begin
        q<=4'b0000;
    end
    else if(enable==1) begin
        if(updown==1) begin
            q<=q+4'b0001;
        end
        else begin
            q<=q-4'b0001;
        end
    end
    else begin
        q<=q;
    end
end
endmodule

OneDrive/Desktop/75/week_4/src/mon_code/tb_counter_4bit.v
module tb_counter_4bit;
    reg rst;
    reg clk;
    reg enable;
    reg updown;
    wire [3:0]q;
    counter_4bit uut(
    .enable(enable),
    .clk(clk), 
    .rst(rst),
    .q(q), 
    .updown(updown)
    );
    always #5 clk=~clk;
    initial begin
        $dumpfile("dump.vcd");
        $dumpvars(0,tb_counter_4bit);
        rst=0;clk=0;updown=0;enable=0;#200
        rst=1;
        #60;
        rst=0;enable=1;updown=1;#120;
        enable=1;updown=0;#200;
        enable=0;updown=1;#200;
        enable=1;updown=1;#400;
        $finish;
    end
endmodule

OneDrive/Desktop/75/week_4/src/mon_code/dump.vcd
$date
	Mon Jun 08 11:30:52 2026
$end
$version
	Icarus Verilog
$end
$timescale
	1s
$end
$scope module tb_counter_4bit $end
$var wire 4 ! q [3:0] $end
$var reg 1 " clk $end
$var reg 1 # enable $end
$var reg 1 $ rst $end
$var reg 1 % updown $end
$scope module uut $end
$var wire 1 " clk $end
$var wire 1 # enable $end
$var wire 1 $ rst $end
$var wire 1 % updown $end
$var reg 4 & q [3:0] $end
$upscope $end
$upscope $end
$enddefinitions $end
#0
$dumpvars
bx &
0%
0$
0#
0"
bx !
$end
#5
1"
#10
0"
#15
1"
#20
0"
#25
1"
#30
0"
#35
1"
#40
0"
#45
1"
#50
0"
#55
1"
#60
0"
#65
1"
#70
0"
#75
1"
#80
0"
#85
1"
#90
0"
#95
1"
#100
0"
#105
1"
#110
0"
#115
1"
#120
0"
#125
1"
#130
0"
#135
1"
#140
0"
#145
1"
#150
0"
#155
1"
#160
0"
#165
1"
#170
0"
#175
1"
#180
0"
#185
1"
#190
0"
#195
1"
#200
0"
1$
#205
b0 !
b0 &
1"
#210
0"
#215
1"
#220
0"
#225
1"
#230
0"
#235
1"
#240
0"
#245
1"
#250
0"
#255
1"
#260
0"
1%
1#
0$
#265
b1 !
b1 &
1"
#270
0"
#275
b10 !
b10 &
1"
#280
0"
#285
b11 !
b11 &
1"
#290
0"
#295
b100 !
b100 &
1"
#300
0"
#305
b101 !
b101 &
1"
#310
0"
#315
b110 !
b110 &
1"
#320
0"
#325
b111 !
b111 &
1"
#330
0"
#335
b1000 !
b1000 &
1"
#340
0"
#345
b1001 !
b1001 &
1"
#350
0"
#355
b1010 !
b1010 &
1"
#360
0"
#365
b1011 !
b1011 &
1"
#370
0"
#375
b1100 !
b1100 &
1"
#380
0"
0%
#385
b1011 !
b1011 &
1"
#390
0"
#395
b1010 !
b1010 &
1"
#400
0"
#405
b1001 !
b1001 &
1"
#410
0"
#415
b1000 !
b1000 &
1"
#420
0"
#425
b111 !
b111 &
1"
#430
0"
#435
b110 !
b110 &
1"
#440
0"
#445
b101 !
b101 &
1"
#450
0"
#455
b100 !
b100 &
1"
#460
0"
#465
b11 !
b11 &
1"
#470
0"
#475
b10 !
b10 &
1"
#480
0"
#485
b1 !
b1 &
1"
#490
0"
#495
b0 !
b0 &
1"
#500
0"
#505
b1111 !
b1111 &
1"
#510
0"
#515
b1110 !
b1110 &
1"
#520
0"
#525
b1101 !
b1101 &
1"
#530
0"
#535
b1100 !
b1100 &
1"
#540
0"
#545
b1011 !
b1011 &
1"
#550
0"
#555
b1010 !
b1010 &
1"
#560
0"
#565
b1001 !
b1001 &
1"
#570
0"
#575
b1000 !
b1000 &
1"
#580
0"
1%
0#
#585
1"
#590
0"
#595
1"
#600
0"
#605
1"
#610
0"
#615
1"
#620
0"
#625
1"
#630
0"
#635
1"
#640
0"
#645
1"
#650
0"
#655
1"
#660
0"
#665
1"
#670
0"
#675
1"
#680
0"
#685
1"
#690
0"
#695
1"
#700
0"
#705
1"
#710
0"
#715
1"
#720
0"
#725
1"
#730
0"
#735
1"
#740
0"
#745
1"
#750
0"
#755
1"
#760
0"
#765
1"
#770
0"
#775
1"
#780
0"
1#
#785
b1001 !
b1001 &
1"
#790
0"
#795
b1010 !
b1010 &
1"
#800
0"
#805
b1011 !
b1011 &
1"
#810
0"
#815
b1100 !
b1100 &
1"
#820
0"
#825
b1101 !
b1101 &
1"
#830
0"
#835
b1110 !
b1110 &
1"
#840
0"
#845
b1111 !
b1111 &
1"
#850
0"
#855
b0 !
b0 &
1"
#860
0"
#865
b1 !
b1 &
1"
#870
0"
#875
b10 !
b10 &
1"
#880
0"
#885
b11 !
b11 &
1"
#890
0"
#895
b100 !
b100 &
1"
#900
0"
#905
b101 !
b101 &
1"
#910
0"
#915
b110 !
b110 &
1"
#920
0"
#925
b111 !
b111 &
1"
#930
0"
#935
b1000 !
b1000 &
1"
#940
0"
#945
b1001 !
b1001 &
1"
#950
0"
#955
b1010 !
b1010 &
1"
#960
0"
#965
b1011 !
b1011 &
1"
#970
0"
#975
b1100 !
b1100 &
1"
#980
0"
#985
b1101 !
b1101 &
1"
#990
0"
#995
b1110 !
b1110 &
1"
#1000
0"
#1005
b1111 !
b1111 &
1"
#1010
0"
#1015
b0 !
b0 &
1"
#1020
0"
#1025
b1 !
b1 &
1"
#1030
0"
#1035
b10 !
b10 &
1"
#1040
0"
#1045
b11 !
b11 &
1"
#1050
0"
#1055
b100 !
b100 &
1"
#1060
0"
#1065
b101 !
b101 &
1"
#1070
0"
#1075
b110 !
b110 &
1"
#1080
0"
#1085
b111 !
b111 &
1"
#1090
0"
#1095
b1000 !
b1000 &
1"
#1100
0"
#1105
b1001 !
b1001 &
1"
#1110
0"
#1115
b1010 !
b1010 &
1"
#1120
0"
#1125
b1011 !
b1011 &
1"
#1130
0"
#1135
b1100 !
b1100 &
1"
#1140
0"
#1145
b1101 !
b1101 &
1"
#1150
0"
#1155
b1110 !
b1110 &
1"
#1160
0"
#1165
b1111 !
b1111 &
1"
#1170
0"
#1175
b0 !
b0 &
1"
