OneDrive/Desktop/75/week_4/src/sat-code/hex_7_display.v
module hex_7_display(
    input [3:0]a,
    output reg[6:0]out
);
    always @(*) begin

        case (a)
            4'h0: out = 7'b0111111;
            4'h1: out = 7'b0000110;
            4'h2: out = 7'b1011011;
            4'h3: out = 7'b1001111;
            4'h4: out = 7'b1100110;
            4'h5: out = 7'b1101101;
            4'h6: out = 7'b1111101;
            4'h7: out = 7'b0000111;
            4'h8: out = 7'b1111111;
            4'h9: out = 7'b1101111;
            4'hA: out = 7'b1110111;
            4'hB: out = 7'b1111100;
            4'hC: out = 7'b0111001;
            4'hD: out = 7'b1011110;
            4'hE: out = 7'b1111001;
            4'hF: out = 7'b1110001;
            default : out=7'b0000000;
        endcase
    end
endmodule

OneDrive/Desktop/75/week_4/src/sat-code/counter_nbit.v
module counter_nbit(
    input wire rst,
    input wire clk,
    output reg [3:0]q

);
always @(posedge clk) begin
    if(rst==1) begin
        q<=4'b0000;
    end
    else if(q==4'b1001) begin
        q<=4'b0000;
    end
    else begin
        q<=q+4'b0001;
    end
    
end
endmodule
//	Modulo-6 counter: reset at count==5 (not 6!). Modulo-10 counter. 
//Modulo-5208 counter (your future UART baud generator). Verify each resets at exactly the right value. Off-by-one is a real and common bug here.
//for 5208 13 bits needed

OneDrive/Desktop/75/week_4/src/sat-code/tb_multi.v
module tb_multi;
    reg clk;
    reg rst;
    wire [6:0]out;
    wire [3:0]inta;
    counter_nbit uut1(
        .clk(clk), .rst(rst), .q(inta)
    );
    hex_7_display uut2(
        .a(inta), .out(out)
    );
    always #5 clk=~clk;
   
   initial begin
        $dumpfile("dump.vcd");
        $dumpvars(0, tb_multi);
        
        // Step 1: Initialize values and apply a startup delay
        clk = 0; rst = 0;#200;
        
        // Step 2: Pulse the Reset high to synchronize the counter
        rst = 1;
        #20;
        rst = 0;
        
        // Step 3: Just wait! Let the system cycle from 0 to 9 on its own
        #300;
        
        $finish;
    end
endmodule

OneDrive/Desktop/75/week_4/src/sat-code/dump.vcd
$date
	Thu Jun 11 16:51:22 2026
$end
$version
	Icarus Verilog
$end
$timescale
	1s
$end
$scope module tb_multi $end
$var wire 7 ! out [6:0] $end
$var wire 4 " inta [3:0] $end
$var reg 1 # clk $end
$var reg 1 $ rst $end
$scope module uut1 $end
$var wire 1 # clk $end
$var wire 1 $ rst $end
$var reg 4 % q [3:0] $end
$upscope $end
$scope module uut2 $end
$var wire 4 & a [3:0] $end
$var reg 7 ' out [6:0] $end
$upscope $end
$upscope $end
$enddefinitions $end
#0
$dumpvars
bx '
bx &
bx %
0$
0#
bx "
bx !
$end
#5
1#
#10
0#
#15
1#
#20
0#
#25
1#
#30
0#
#35
1#
#40
0#
#45
1#
#50
0#
#55
1#
#60
0#
#65
1#
#70
0#
#75
1#
#80
0#
#85
1#
#90
0#
#95
1#
#100
0#
#105
1#
#110
0#
#115
1#
#120
0#
#125
1#
#130
0#
#135
1#
#140
0#
#145
1#
#150
0#
#155
1#
#160
0#
#165
1#
#170
0#
#175
1#
#180
0#
#185
1#
#190
0#
#195
1#
#200
0#
1$
#205
b111111 !
b111111 '
b0 "
b0 %
b0 &
1#
#210
0#
#215
1#
#220
0#
0$
#225
b110 !
b110 '
b1 "
b1 %
b1 &
1#
#230
0#
#235
b1011011 !
b1011011 '
b10 "
b10 %
b10 &
1#
#240
0#
#245
b1001111 !
b1001111 '
b11 "
b11 %
b11 &
1#
#250
0#
#255
b1100110 !
b1100110 '
b100 "
b100 %
b100 &
1#
#260
0#
#265
b1101101 !
b1101101 '
b101 "
b101 %
b101 &
1#
#270
0#
#275
b1111101 !
b1111101 '
b110 "
b110 %
b110 &
1#
#280
0#
#285
b111 !
b111 '
b111 "
b111 %
b111 &
1#
#290
0#
#295
b1111111 !
b1111111 '
b1000 "
b1000 %
b1000 &
1#
#300
0#
#305
b1101111 !
b1101111 '
b1001 "
b1001 %
b1001 &
1#
#310
0#
#315
b111111 !
b111111 '
b0 "
b0 %
b0 &
1#
#320
0#
#325
b110 !
b110 '
b1 "
b1 %
b1 &
1#
#330
0#
#335
b1011011 !
b1011011 '
b10 "
b10 %
b10 &
1#
#340
0#
#345
b1001111 !
b1001111 '
b11 "
b11 %
b11 &
1#
#350
0#
#355
b1100110 !
b1100110 '
b100 "
b100 %
b100 &
1#
#360
0#
#365
b1101101 !
b1101101 '
b101 "
b101 %
b101 &
1#
#370
0#
#375
b1111101 !
b1111101 '
b110 "
b110 %
b110 &
1#
#380
0#
#385
b111 !
b111 '
b111 "
b111 %
b111 &
1#
#390
0#
#395
b1111111 !
b1111111 '
b1000 "
b1000 %
b1000 &
1#
#400
0#
#405
b1101111 !
b1101111 '
b1001 "
b1001 %
b1001 &
1#
#410
0#
#415
b111111 !
b111111 '
b0 "
b0 %
b0 &
1#
#420
0#
#425
b110 !
b110 '
b1 "
b1 %
b1 &
1#
#430
0#
#435
b1011011 !
b1011011 '
b10 "
b10 %
b10 &
1#
#440
0#
#445
b1001111 !
b1001111 '
b11 "
b11 %
b11 &
1#
#450
0#
#455
b1100110 !
b1100110 '
b100 "
b100 %
b100 &
1#
#460
0#
#465
b1101101 !
b1101101 '
b101 "
b101 %
b101 &
1#
#470
0#
#475
b1111101 !
b1111101 '
b110 "
b110 %
b110 &
1#
#480
0#
#485
b111 !
b111 '
b111 "
b111 %
b111 &
1#
#490
0#
#495
b1111111 !
b1111111 '
b1000 "
b1000 %
b1000 &
1#
#500
0#
#505
b1101111 !
b1101111 '
b1001 "
b1001 %
b1001 &
1#
#510
0#
#515
b111111 !
b111111 '
b0 "
b0 %
b0 &
1#
