OneDrive/Desktop/75/week_4/src/ring_counter/ring_counter.v
module ring_counter(
    input wire clk,
    input wire rst,
    output reg [3:0]q
);
always @(posedge clk) begin
    if (rst==1) begin
        q<=4'b1000;
    end
    else begin
        q<={q[0],q[3:1]};
    end
end
endmodule

OneDrive/Desktop/75/week_4/src/ring_counter/tb_ring_counter.v
module tb_ring_counter;
    reg clk;
    reg rst;
    wire[3:0]q;
    ring_counter uut(
        .clk(clk), .rst(rst), .q(q)
    );
    always #5 clk=~clk;
    initial begin
        $dumpfile("dump.vcd");
        $dumpvars(0,tb_ring_counter);
        rst=0;clk=0;#3;
        rst=1;#3;
        rst=0;#100;
        $finish;
    end
endmodule

OneDrive/Desktop/75/week_4/src/ring_counter/dump.vcd
$date
	Wed Jun 10 16:05:59 2026
$end
$version
	Icarus Verilog
$end
$timescale
	1s
$end
$scope module tb_ring_counter $end
$var wire 4 ! q [3:0] $end
$var reg 1 " clk $end
$var reg 1 # rst $end
$scope module uut $end
$var wire 1 " clk $end
$var wire 1 # rst $end
$var reg 4 $ q [3:0] $end
$upscope $end
$upscope $end
$enddefinitions $end
#0
$dumpvars
bx $
0#
0"
bx !
$end
#3
1#
#5
b1000 !
b1000 $
1"
#6
0#
#10
0"
#15
b100 !
b100 $
1"
#20
0"
#25
b10 !
b10 $
1"
#30
0"
#35
b1 !
b1 $
1"
#40
0"
#45
b1000 !
b1000 $
1"
#50
0"
#55
b100 !
b100 $
1"
#60
0"
#65
b10 !
b10 $
1"
#70
0"
#75
b1 !
b1 $
1"
#80
0"
#85
b1000 !
b1000 $
1"
#90
0"
#95
b100 !
b100 $
1"
#100
0"
#105
b10 !
b10 $
1"
