OneDrive/Desktop/75/week_4/src/clock_divider/clock_divider.v
module clock_divider #(parameter DIVISOR =4
)(
    input wire clk_in,
    output reg clk_out,
    input wire rst
);
reg [3:0] count;
always @(posedge clk_in) begin
    if(rst==1) begin
        count<=4'b0000;
        clk_out<=1'b0;
    end
    else begin
        if(count==(DIVISOR/2)-1) begin
            count<=4'b0000;
            clk_out<=~clk_out;
        end
        else begin
            count<=count +4'b0001;
        end
    end
end
endmodule

OneDrive/Desktop/75/week_4/src/clock_divider/tb_clock_divider.v
module tb_clock_divider;
    reg clk_in;
    reg rst;
    wire clk_out;
    clock_divider uut(
        .rst(rst), .clk_in(clk_in), .clk_out(clk_out)

    );
    always #5 clk_in=~clk_in;
    initial begin
        $dumpfile("dump.vcd");
        $dumpvars(0,tb_clock_divider);
        rst=0;clk_in=0;#3;
        rst=1;
        #3;
        rst=0;
        #300;
        $finish;
    end
endmodule

OneDrive/Desktop/75/week_4/src/clock_divider/dump.vcd
$date
	Thu Jun 11 14:14:20 2026
$end
$version
	Icarus Verilog
$end
$timescale
	1s
$end
$scope module tb_clock_divider $end
$var wire 1 ! clk_out $end
$var reg 1 " clk_in $end
$var reg 1 # rst $end
$scope module uut $end
$var wire 1 " clk_in $end
$var wire 1 # rst $end
$var reg 1 ! clk_out $end
$var reg 4 $ count [3:0] $end
$upscope $end
$upscope $end
$enddefinitions $end
#0
$dumpvars
bx $
0#
0"
x!
$end
#3
1#
#5
0!
b0 $
1"
#6
0#
#10
0"
#15
b1 $
1"
#20
0"
#25
1!
b0 $
1"
#30
0"
#35
b1 $
1"
#40
0"
#45
0!
b0 $
1"
#50
0"
#55
b1 $
1"
#60
0"
#65
1!
b0 $
1"
#70
0"
#75
b1 $
1"
#80
0"
#85
0!
b0 $
1"
#90
0"
#95
b1 $
1"
#100
0"
#105
1!
b0 $
1"
#110
0"
#115
b1 $
1"
#120
0"
#125
0!
b0 $
1"
#130
0"
#135
b1 $
1"
#140
0"
#145
1!
b0 $
1"
#150
0"
#155
b1 $
1"
#160
0"
#165
0!
b0 $
1"
#170
0"
#175
b1 $
1"
#180
0"
#185
1!
b0 $
1"
#190
0"
#195
b1 $
1"
#200
0"
#205
0!
b0 $
1"
#210
0"
#215
b1 $
1"
#220
0"
#225
1!
b0 $
1"
#230
0"
#235
b1 $
1"
#240
0"
#245
0!
b0 $
1"
#250
0"
#255
b1 $
1"
#260
0"
#265
1!
b0 $
1"
#270
0"
#275
b1 $
1"
#280
0"
#285
0!
b0 $
1"
#290
0"
#295
b1 $
1"
#300
0"
#305
1!
b0 $
1"
